Workbook

Sheet README
A1: EXOTIC & COLLECTOR AUTOMOBILE MGA — UNDERWRITING BORDEREAUX
A2: Monthly delegated authority underwriting reporting to the Lloyd's syndicate panel. Distinct from the claims bordereaux — this reports bound policies, not claims.
B4: SHEETS IN THIS WORKBOOK
B6: Header | C6: Contract identification, reporting period, binding and discount authority limits, syndicate participation table, and a live submission control summary linking to the bordereaux data.
B7: UW Bordereaux | C7: The data sheet. One row per policy per reporting period. 56 columns, 200 pre-formatted rows. Blue columns are for entry; grey columns calculate. Report every risk — new business, renewals, endorsements, cancellations.
B8: Reconciliation | C8: Premium reconciliation (GWP minus commission equals net to capacity; total due reconciles through fees and tax) plus twelve automated submission control checks. Run before every submission.
B9: Field Definitions | C9: Every column explained with its population rule and source.
B10: Lists | C10: Source of every drop-down. Amend here to change available options.
B12: HOW THIS BORDEREAUX DIFFERS FROM THE CLAIMS BORDEREAUX
B14: - The underwriting bordereaux reports POLICIES BOUND. The claims bordereaux reports CLAIMS NOTIFIED. Both go to the same syndicate panel under the same binding authority, but they are separate documents with separate submission schedules.
B15: - The underwriting bordereaux is typically submitted monthly (or quarterly for lower-volume binders) and covers every risk bound, renewed, endorsed or cancelled in the period. It is the primary document the syndicates use to monitor premium volume, rate adequacy and class mix.
B16: - Rate adequacy is the metric the lead syndicate watches most closely on a delegated motor book. The rate adequacy column and the Header summary are the underwriting bdx's equivalent of the loss ratio on the claims bdx — they tell the syndicate whether the coverholder is generating business at an adequate price.
B17: - This bordereaux does not feed the claims bdx automatically — the two documents are matched by certificate number and insured name at the syndicate level during the bureau reconciliation process.
B19: HOW TO USE
B21: - Complete the Header sheet before the first submission: UMR, coverholder name, PIN, reporting period, authority limits. These cells carry through to every calculation in the bordereaux data sheet.
B22: - Enter one row per policy. For endorsements and renewals, carry the original certificate number and set the movement type accordingly — do not create a new certificate number.
B23: - The technical premium column (AB) must be entered manually or copied from the Portfolio Register. It represents the rate-adequate price the rater produced before any UW judgement adjustment. If it is left blank, the GWP, rate adequacy and all downstream commission calculations will be blank too.
B24: - Surplus lines tax rate (column AF) must be entered for every bound risk. The formula calculates the dollar amount, but the rate itself is your responsibility — verify it with the stamping office or your filing service before the bordereaux is sent.
B25: - Run the Reconciliation sheet before every submission. Any FAIL must be resolved. A WARN on rate adequacy should be noted and explained to the lead syndicate; it does not block submission but will be questioned.
B26: - Six specimen risks are pre-loaded to show the intended level of detail. Delete them before issuing to the syndicates.
B28: IMPORTANT — This template follows the general structure and field set of Lloyd's coverholder underwriting reporting, but it is NOT a certified Lloyd's Coverholder Reporting Standards file. Before your first submission, obtain the exact required template, mandatory field list and column order from your Lloyd's broker or the lead syndicate's delegated authority team. Requirements differ by syndicate, by class and by year of account, and they change annually. The LCRS v5.2 schema (and its successors) governs the accepted electronic format.

Sheet Header
A1: UNDERWRITING BORDEREAUX — HEADER AND SUBMISSION DETAILS
A2: Complete before every submission. These fields identify the contract and reporting period.
B3: Commission stack: 25% total = 12.5% broker + 12.5% Torque Underwriters (MGA). Net to capacity 75%. | H3: Total ceding | I3: 0.25 | J3: Broker | K3: 0.125 | L3: Torque (MGA) | M3: 0.125 | N3: PC hurdle | O3: 0.6 | P3: PC share | Q3: 0.15 | R3: =IF(ROUND($K$3+$M$3-$I$3,6)=0,"Splits foot — OK","ERROR: broker + Torque <> total")
B4: SECTION A — CONTRACT IDENTIFICATION
B5: Unique Market Reference (UMR) | C5: B1234EXOTIC26 | G5: Must match exactly on every submission and on every certificate issued under the binder.
B6: Binding authority reference | C6: BA-EXO-2026-01
B7: Coverholder name | C7: [Your MGA legal entity name]
B8: Lloyd's coverholder PIN | C8: [PIN] | G8: Issued on coverholder approval. Required on every submission.
B9: Risk code | C9: MT | G9: Lloyd's risk code. MT = Motor. Confirm with your Lloyd's broker.
B10: Year of account | C10: 2026
B11: Class of business | C11: Exotic, supercar and collector automobile
B12: Reporting period start | C12: 46204
B13: Reporting period end | C13: 46234
B14: Submission date | C14: 46244 | G14: Most binders require submission within 15–30 days of period end. Verify yours.
B15: Prepared by | C15: [Name, title]
B16: Reporting currency | C16: USD
B17: Settlement currency | C17: USD
B18: Coverholder binding authority limit (AV) | C18: $2,000,000 | G18: Per Technical Premium row 16. Risks above this value require individual referral.
B19: Discount authority limit | C19: −15.0% | G19: Per Technical Premium row 19. Risks priced beyond this require senior approval.
B20: Minimum premium per policy | C20: 5000 | G20: Confirm in the binding authority wording. Applies irrespective of the formula result.
B22: SECTION B — SYNDICATE PARTICIPATION AND SHARE ALLOCATION
B23: Syndicate | C23: Managing agent | D23: Line % (share of risk) | E23: GWP at line | F23: Technical prem at line | G23: NET TO CAPACITY at line
B24: 2623 / 623 | C24: Beazley Furlonge Ltd | D24: 0.1 | E24: =(SUMIF('UW Bordereaux'!$D$5:$D$662,"Bound*",'UW Bordereaux'!$AD$5:$AD$662))*$D24 | F24: =(SUMIF('UW Bordereaux'!$D$5:$D$662,"Bound*",'UW Bordereaux'!$AB$5:$AB$662))*$D24 | G24: =(SUMIF('UW Bordereaux'!$D$5:$D$662,"Bound*",'UW Bordereaux'!$AQ$5:$AQ$662))*$D24
B25: 33 | C25: Hiscox Syndicates Ltd | D25: 0.1 | E25: =(SUMIF('UW Bordereaux'!$D$5:$D$662,"Bound*",'UW Bordereaux'!$AD$5:$AD$662))*$D25 | F25: =(SUMIF('UW Bordereaux'!$D$5:$D$662,"Bound*",'UW Bordereaux'!$AB$5:$AB$662))*$D25 | G25: =(SUMIF('UW Bordereaux'!$D$5:$D$662,"Bound*",'UW Bordereaux'!$AQ$5:$AQ$662))*$D25
B26: 1084 | C26: Chaucer Syndicates Ltd | D26: 0.1 | E26: =(SUMIF('UW Bordereaux'!$D$5:$D$662,"Bound*",'UW Bordereaux'!$AD$5:$AD$662))*$D26 | F26: =(SUMIF('UW Bordereaux'!$D$5:$D$662,"Bound*",'UW Bordereaux'!$AB$5:$AB$662))*$D26 | G26: =(SUMIF('UW Bordereaux'!$D$5:$D$662,"Bound*",'UW Bordereaux'!$AQ$5:$AQ$662))*$D26
B27: 4020 | C27: Ark Syndicate Management | D27: 0.1 | E27: =(SUMIF('UW Bordereaux'!$D$5:$D$662,"Bound*",'UW Bordereaux'!$AD$5:$AD$662))*$D27 | F27: =(SUMIF('UW Bordereaux'!$D$5:$D$662,"Bound*",'UW Bordereaux'!$AB$5:$AB$662))*$D27 | G27: =(SUMIF('UW Bordereaux'!$D$5:$D$662,"Bound*",'UW Bordereaux'!$AQ$5:$AQ$662))*$D27
B28: 2987 | C28: Brit Syndicates Ltd | D28: 0.1 | E28: =(SUMIF('UW Bordereaux'!$D$5:$D$662,"Bound*",'UW Bordereaux'!$AD$5:$AD$662))*$D28 | F28: =(SUMIF('UW Bordereaux'!$D$5:$D$662,"Bound*",'UW Bordereaux'!$AB$5:$AB$662))*$D28 | G28: =(SUMIF('UW Bordereaux'!$D$5:$D$662,"Bound*",'UW Bordereaux'!$AQ$5:$AQ$662))*$D28
B29: 4444 | C29: Canopius Managing Agents | D29: 0.1 | E29: =(SUMIF('UW Bordereaux'!$D$5:$D$662,"Bound*",'UW Bordereaux'!$AD$5:$AD$662))*$D29 | F29: =(SUMIF('UW Bordereaux'!$D$5:$D$662,"Bound*",'UW Bordereaux'!$AB$5:$AB$662))*$D29 | G29: =(SUMIF('UW Bordereaux'!$D$5:$D$662,"Bound*",'UW Bordereaux'!$AQ$5:$AQ$662))*$D29
B30: 1969 | C30: Apollo Syndicate Management | D30: 0.1 | E30: =(SUMIF('UW Bordereaux'!$D$5:$D$662,"Bound*",'UW Bordereaux'!$AD$5:$AD$662))*$D30 | F30: =(SUMIF('UW Bordereaux'!$D$5:$D$662,"Bound*",'UW Bordereaux'!$AB$5:$AB$662))*$D30 | G30: =(SUMIF('UW Bordereaux'!$D$5:$D$662,"Bound*",'UW Bordereaux'!$AQ$5:$AQ$662))*$D30
B31: 1274 | C31: Antares Managing Agency | D31: 0.1 | E31: =(SUMIF('UW Bordereaux'!$D$5:$D$662,"Bound*",'UW Bordereaux'!$AD$5:$AD$662))*$D31 | F31: =(SUMIF('UW Bordereaux'!$D$5:$D$662,"Bound*",'UW Bordereaux'!$AB$5:$AB$662))*$D31 | G31: =(SUMIF('UW Bordereaux'!$D$5:$D$662,"Bound*",'UW Bordereaux'!$AQ$5:$AQ$662))*$D31
B32: 2001 | C32: MS Amlin Underwriting | D32: 0.1 | E32: =(SUMIF('UW Bordereaux'!$D$5:$D$662,"Bound*",'UW Bordereaux'!$AD$5:$AD$662))*$D32 | F32: =(SUMIF('UW Bordereaux'!$D$5:$D$662,"Bound*",'UW Bordereaux'!$AB$5:$AB$662))*$D32 | G32: =(SUMIF('UW Bordereaux'!$D$5:$D$662,"Bound*",'UW Bordereaux'!$AQ$5:$AQ$662))*$D32
B33: 1414 | C33: Ascot Underwriting Ltd | D33: 0.1 | E33: =(SUMIF('UW Bordereaux'!$D$5:$D$662,"Bound*",'UW Bordereaux'!$AD$5:$AD$662))*$D33 | F33: =(SUMIF('UW Bordereaux'!$D$5:$D$662,"Bound*",'UW Bordereaux'!$AB$5:$AB$662))*$D33 | G33: =(SUMIF('UW Bordereaux'!$D$5:$D$662,"Bound*",'UW Bordereaux'!$AQ$5:$AQ$662))*$D33
C34: PANEL TOTAL | D34: =SUM(D24:D33) | E34: =SUMIF('UW Bordereaux'!$D$5:$D$662,"Bound*",'UW Bordereaux'!$AD$5:$AD$662) | F34: =SUMIF('UW Bordereaux'!$D$5:$D$662,"Bound*",'UW Bordereaux'!$AB$5:$AB$662) | G34: =SUMIF('UW Bordereaux'!$D$5:$D$662,"Bound*",'UW Bordereaux'!$AQ$5:$AQ$662)
D35: =IF(ROUND(D34,6)=1,"Panel signs 100% — OK","ERROR: panel signs "&TEXT(D34,"0.00%"))
B37: SECTION C — SUBMISSION CONTROL SUMMARY (live from UW Bordereaux)
B38: Policies reported this period | C38: =COUNTA('UW Bordereaux'!$A$5:$A$662)
B39: of which bound | C39: =COUNTIF('UW Bordereaux'!$D$5:$D$662,"Bound*")
B40: of which declined / lapsed | C40: =COUNTIF('UW Bordereaux'!$D$5:$D$662,"Declined")+COUNTIF('UW Bordereaux'!$D$5:$D$662,"Cancelled")+COUNTIF('UW Bordereaux'!$D$5:$D$662,"Lapsed")
B41: TOTAL GWP BOUND | C41: =SUMIF('UW Bordereaux'!$D$5:$D$662,"Bound*",'UW Bordereaux'!$AD$5:$AD$662)
B42: TOTAL TECHNICAL PREMIUM | C42: =SUMIF('UW Bordereaux'!$D$5:$D$662,"Bound*",'UW Bordereaux'!$AB$5:$AB$662)
B43: PORTFOLIO RATE ADEQUACY | C43: =IFERROR((SUMIF('UW Bordereaux'!$D$5:$D$662,"Bound*",'UW Bordereaux'!$AD$5:$AD$662))/(SUMIF('UW Bordereaux'!$D$5:$D$662,"Bound*",'UW Bordereaux'!$AB$5:$AB$662)),0)
B44: Total net premium to capacity | C44: =SUMIF('UW Bordereaux'!$D$5:$D$662,"Bound*",'UW Bordereaux'!$AQ$5:$AQ$662)
B45: Total policy fees collected | C45: =SUMIF('UW Bordereaux'!$D$5:$D$662,"Bound*",'UW Bordereaux'!$AE$5:$AE$662)
B46: Total surplus lines tax collected | C46: =SUMIF('UW Bordereaux'!$D$5:$D$662,"Bound*",'UW Bordereaux'!$AH$5:$AH$662)
B47: Risks above auto-bind limit | C47: =COUNTIFS('UW Bordereaux'!$AD$5:$AD$662,">="&Header!$C$18,'UW Bordereaux'!$D$5:$D$662,"Bound*")
B48: Risks bound beyond discount auth. | C48: =COUNTIF('UW Bordereaux'!$AL$5:$AL$662,"BEYOND AUTHORITY")
B49: Missing certificate numbers | C49: =COUNTA('UW Bordereaux'!$A$5:$A$662)-COUNTIF('UW Bordereaux'!$D$5:$D$662,"Bound*")-COUNTIF('UW Bordereaux'!$D$5:$D$662,"Declined")-COUNTIF('UW Bordereaux'!$D$5:$D$662,"Cancelled")-COUNTIF('UW Bordereaux'!$D$5:$D$662,"Lapsed")-COUNTIF('UW Bordereaux'!$D$5:$D$662,"Quoted*")-COUNTIF('UW Bordereaux'!$D$5:$D$662,"Void")-COUNTIF('UW Bordereaux'!$D$5:$D$662,"Reinstatement")
B50: Rows failing mandatory checks | C50: =COUNTIF('UW Bordereaux'!$AX$5:$AX$662,"FAIL*")

Sheet UW Bordereaux
A1: UNDERWRITING BORDEREAUX
A2: One row per policy per reporting period. Blue columns are for entry; grey columns calculate from the Portfolio Register or from other inputs. Report every bound risk — new business, renewals and endorsements.
A3: POLICY IDENTIFICATION | H3: RISK DATA | R3: GARAGING & CAT | W3: COVERAGE TERMS | AC3: PREMIUM — 100% GROSS | AO3: COMMISSION & NET | AT3: RATING METRICS | AZ3: CONTROLS | BE3: DATA QUALITY
A4: Certificate / policy ref | B4: Named insured | C4: Effective date | D4: Binding status | E4: Movement type | F4: UMR | G4: Year of account | H4: Vehicle year | I4: Make | J4: Model | K4: VIN / chassis | L4: Vehicle class | M4: Agreed value (USD) | N4: Policy type | O4: Usage description | P4: Annual mileage band | Q4: Garaging state | R4: Garaging ZIP | S4: Catastrophe zone | T4: Zone multiplier | U4: Cat deductible | V4: Valuation basis | W4: PD deductible | X4: Liability limit (CSL) | Y4: Endorsements / special terms | Z4: Conditions | AA4: Surplus lines / admitted | AB4: Technical premium (100%) | AC4: UW judgement adj % | AD4: GROSS WRITTEN PREMIUM (100%) | AE4: Policy fee (100%) | AF4: Inspection / appraisal fee | AG4: Surplus lines tax % | AH4: Surplus lines tax $ | AI4: Stamping fee $ | AJ4: TOTAL DUE FROM INSURED (100%) | AK4: Rate adequacy check | AL4: Bind band | AM4: Total ceding commission % | AN4: Commission $ (100%) | AO4: Broker commission $ 12.5% (100%) | AP4: Torque (MGA) commission $ 12.5% (100%) | AQ4: NET TO CAPACITY 75% (100%) | AR4: GWP at signed line | AS4: Tech prem at signed line | AT4: Technical rate per $100 | AU4: Charged rate per $100 | AV4: Portfolio rate adequacy | AW4: Profit commission accrual | AX4: MANDATORY FIELD CHECK | AY4: Above auto-bind limit? | AZ4: Min premium met? | BA4: Surplus lines tax verified? | BB4: Signed by approver? | BC4: Notes | BE4: Class / year consistency | BF4: Row foots to GWP
A5: CANON-202602-004664 | B5: Horace Bellandi | C5: 46071 | D5: Bound - within authority | E5: New business | F5: B1234EXOTIC26 | G5: =IF($A5="","",IF($C5="","",YEAR($C5))) | H5: 2014 | I5: Lamborghini | J5: Huracan EVO | K5: CH4SNLTCEGRLJ0UEW | L5: 03 - Supercar | M5: 670000 | N5: Personal | O5: Personal - regular use | P5: Under 1,000 | Q5: Iowa | R5: 50309 | S5: Severe convective - hail alley (high) | T5: =IF($A5="","",IF($S5="","",IFERROR(INDEX('[1]natural catastrophe'!$D$6:$D$17,MATCH($S5,'[1]natural catastrophe'!$B$6:$B$17,0)),"?"))) | U5: $5,000 | V5: Agreed Value | W5: $1,000 | X5: $1,000,000 CSL | AA5: Surplus Lines | AB5: 11614.57 | AC5: 0 | AD5: =IF(ISNUMBER($AB5),$AB5*(1+N($AC5)),"") | AE5: 350 | AF5: 0 | AH5: =IF(ISNUMBER($AD5),($AD5+$AE5+$AF5)*$AG5,"") | AJ5: =IF(ISNUMBER($AD5),SUM($AD5:$AH5),"") | AK5: =IF(AND(ISNUMBER($AB5),ISNUMBER($AD5)),IF($AB5>0,$AD5/$AB5,""),"") | AL5: At technical | AM5: =IF(ISNUMBER($AD5),Header!$I$3,"") | AN5: =IF(ISNUMBER($AD5),$AO5+$AP5,"") | AO5: =IF(ISNUMBER($AD5),ROUND($AD5*Header!$K$3,2),"") | AP5: =IF(ISNUMBER($AD5),ROUND($AD5*Header!$M$3,2),"") | AQ5: =IF(ISNUMBER($AD5),ROUND($AD5,2)-$AO5-$AP5,"") | AR5: =IF(ISNUMBER($AD5),IF(Header!$D$34="","?",$AD5*Header!$D$34),"") | AS5: =IF(ISNUMBER($AB5),IF(Header!$D$34="","?",$AB5*Header!$D$34),"") | AT5: =IF(AND(ISNUMBER($AB5),$M5>0),$AB5/$M5*100,"") | AU5: =IF(AND(ISNUMBER($AD5),$M5>0),$AD5/$M5*100,"") | AV5: =IF(AND(ISNUMBER($AB5),ISNUMBER($AD5),ABS($AB5)>0),$AD5/$AB5,"") | AW5: =IF(ISNUMBER($AD5),MAX(0,(1-0.55-Header!$O$3)*Header!$Q$3*$AQ5),"") | AX5: =IF($A5="","",IF(TRIM(IF($A5="","Missing certificate ref. ","") & IF($C5="","Missing effective date. ","") & IF($D5="","Missing binding status. ","") & IF($E5="","Missing movement type. ","") & IF($I5="","Missing make. ","") & IF($L5="","Missing vehicle class. ","") & IF($M5="","Missing agreed value. ","") & IF($N5="","Missing policy type. ","") & IF($Q5="","Missing garaging state. ","") & IF($R5="","Missing garaging ZIP. ","") & IF($S5="","Missing cat zone. ","") & IF($V5="","Missing valuation basis. ","") & IF($W5="","Missing PD deductible. ","") & IF($X5="","Missing liability limit. ","") & IF($AB5="","Missing technical premium. ","") & IF($AF5="","Missing surplus lines tax %. ",""))="","PASS","FAIL: "&TRIM(IF($A5="","Missing certificate ref. ","") & IF($C5="","Missing effective date. ","") & IF($D5="","Missing binding status. ","") & IF($E5="","Missing movement type. ","") & IF($I5="","Missing make. ","") & IF($L5="","Missing vehicle class. ","") & IF($M5="","Missing agreed value. ","") & IF($N5="","Missing policy type. ","") & IF($Q5="","Missing garaging state. ","") & IF($R5="","Missing garaging ZIP. ","") & IF($S5="","Missing cat zone. ","") & IF($V5="","Missing valuation basis. ","") & IF($W5="","Missing PD deductible. ","") & IF($X5="","Missing liability limit. ","") & IF($AB5="","Missing technical premium. ","") & IF($AF5="","Missing surplus lines tax %. ","")))) | AY5: =IF($M5="","",IF(ISNUMBER($M5),IF($M5>=Header!$C$18,"YES — refer","No"),"")) | AZ5: =IF($AD5="","",IF(ISNUMBER($AD5),IF($AD5<Header!$C$20,"BELOW MIN PREMIUM","OK"),"")) | BA5: Yes | BB5: Yes | BC5: Synthetic demo data | BE5: =IF(OR($A5="",$L5="",$H5=""),"",IF(AND(LEFT($L5,2)="06",$H5>1945),"FAIL - pre-war class, year "&$H5,IF(AND(LEFT($L5,2)="07",OR($H5<1946,$H5>1972)),"FAIL - 1946-72 class, year "&$H5,IF(AND(LEFT($L5,2)="08",OR($H5<1973,$H5>1999)),"FAIL - 1973-99 class, year "&$H5,IF(AND(LEFT($L5,2)="09",OR($H5<2000,$H5>2010)),"FAIL - 2000-10 class, year "&$H5,"OK"))))) | BF5: =IF($AD5="","",IF(ROUND($AO5+$AP5+$AQ5-$AD5,2)=0,"OK","FAIL - out by "&TEXT($AO5+$AP5+$AQ5-$AD5,"$0.00")))
A6: CANON-202602-004665 | B6: Anouk Thistlewood | C6: 46059 | D6: Bound - within authority | E6: New business | F6: B1234EXOTIC26 | G6: =IF($A6="","",IF($C6="","",YEAR($C6))) | H6: 1978 | I6: Bentley | J6: Continental GT | K6: 2T9H6GZA4TN9SYL7F | L6: 02 - Sports / GT | M6: 285000 | N6: Personal | O6: Personal - regular use | P6: 2,500 - 5,000 | Q6: Vermont | R6: 05601 | S6: Low hazard - inland benign | T6: =IF($A6="","",IF($S6="","",IFERROR(INDEX('[1]natural catastrophe'!$D$6:$D$17,MATCH($S6,'[1]natural catastrophe'!$B$6:$B$17,0)),"?"))) | U6: $5,000 | V6: Agreed Value | W6: $1,000 | X6: $1,000,000 CSL | AA6: Surplus Lines | AB6: 4325.91 | AC6: 0 | AD6: =IF(ISNUMBER($AB6),$AB6*(1+N($AC6)),"") | AE6: 350 | AF6: 0 | AH6: =IF(ISNUMBER($AD6),($AD6+$AE6+$AF6)*$AG6,"") | AJ6: =IF(ISNUMBER($AD6),SUM($AD6:$AH6),"") | AK6: =IF(AND(ISNUMBER($AB6),ISNUMBER($AD6)),IF($AB6>0,$AD6/$AB6,""),"") | AL6: At technical | AM6: =IF(ISNUMBER($AD6),Header!$I$3,"") | AN6: =IF(ISNUMBER($AD6),$AO6+$AP6,"") | AO6: =IF(ISNUMBER($AD6),ROUND($AD6*Header!$K$3,2),"") | AP6: =IF(ISNUMBER($AD6),ROUND($AD6*Header!$M$3,2),"") | AQ6: =IF(ISNUMBER($AD6),ROUND($AD6,2)-$AO6-$AP6,"") | AR6: =IF(ISNUMBER($AD6),IF(Header!$D$34="","?",$AD6*Header!$D$34),"") | AS6: =IF(ISNUMBER($AB6),IF(Header!$D$34="","?",$AB6*Header!$D$34),"") | AT6: =IF(AND(ISNUMBER($AB6),$M6>0),$AB6/$M6*100,"") | AU6: =IF(AND(ISNUMBER($AD6),$M6>0),$AD6/$M6*100,"") | AV6: =IF(AND(ISNUMBER($AB6),ISNUMBER($AD6),ABS($AB6)>0),$AD6/$AB6,"") | AW6: =IF(ISNUMBER($AD6),MAX(0,(1-0.55-Header!$O$3)*Header!$Q$3*$AQ6),"") | AX6: =IF($A6="","",IF(TRIM(IF($A6="","Missing certificate ref. ","") & IF($C6="","Missing effective date. ","") & IF($D6="","Missing binding status. ","") & IF($E6="","Missing movement type. ","") & IF($I6="","Missing make. ","") & IF($L6="","Missing vehicle class. ","") & IF($M6="","Missing agreed value. ","") & IF($N6="","Missing policy type. ","") & IF($Q6="","Missing garaging state. ","") & IF($R6="","Missing garaging ZIP. ","") & IF($S6="","Missing cat zone. ","") & IF($V6="","Missing valuation basis. ","") & IF($W6="","Missing PD deductible. ","") & IF($X6="","Missing liability limit. ","") & IF($AB6="","Missing technical premium. ","") & IF($AF6="","Missing surplus lines tax %. ",""))="","PASS","FAIL: "&TRIM(IF($A6="","Missing certificate ref. ","") & IF($C6="","Missing effective date. ","") & IF($D6="","Missing binding status. ","") & IF($E6="","Missing movement type. ","") & IF($I6="","Missing make. ","") & IF($L6="","Missing vehicle class. ","") & IF($M6="","Missing agreed value. ","") & IF($N6="","Missing policy type. ","") & IF($Q6="","Missing garaging state. ","") & IF($R6="","Missing garaging ZIP. ","") & IF($S6="","Missing cat zone. ","") & IF($V6="","Missing valuation basis. ","") & IF($W6="","Missing PD deductible. ","") & IF($X6="","Missing liability limit. ","") & IF($AB6="","Missing technical premium. ","") & IF($AF6="","Missing surplus lines tax %. ","")))) | AY6: =IF($M6="","",IF(ISNUMBER($M6),IF($M6>=Header!$C$18,"YES — refer","No"),"")) | AZ6: =IF($AD6="","",IF(ISNUMBER($AD6),IF($AD6<Header!$C$20,"BELOW MIN PREMIUM","OK"),"")) | BA6: Yes | BB6: Yes | BC6: Synthetic demo data | BE6: =IF(OR($A6="",$L6="",$H6=""),"",IF(AND(LEFT($L6,2)="06",$H6>1945),"FAIL - pre-war class, year "&$H6,IF(AND(LEFT($L6,2)="07",OR($H6<1946,$H6>1972)),"FAIL - 1946-72 class, year "&$H6,IF(AND(LEFT($L6,2)="08",OR($H6<1973,$H6>1999)),"FAIL - 1973-99 class, year "&$H6,IF(AND(LEFT($L6,2)="09",OR($H6<2000,$H6>2010)),"FAIL - 2000-10 class, year "&$H6,"OK"))))) | BF6: =IF($AD6="","",IF(ROUND($AO6+$AP6+$AQ6-$AD6,2)=0,"OK","FAIL - out by "&TEXT($AO6+$AP6+$AQ6-$AD6,"$0.00")))
A7: CANON-202602-004666 | B7: Emiliano Fairweather | C7: 46064 | D7: Bound - within authority | E7: New business | F7: B1234EXOTIC26 | G7: =IF($A7="","",IF($C7="","",YEAR($C7))) | H7: 2010 | I7: Mercedes-Benz | J7: AMG GT | K7: ZG7W84T9AT0Z2X9TK | L7: 02 - Sports / GT | M7: 1030000 | N7: Personal | O7: Personal - regular use | P7: 1,000 - 2,500 | Q7: Massachusetts | R7: 02108 | S7: Tier 3 - Coastal wind (25-100 miles) | T7: =IF($A7="","",IF($S7="","",IFERROR(INDEX('[1]natural catastrophe'!$D$6:$D$17,MATCH($S7,'[1]natural catastrophe'!$B$6:$B$17,0)),"?"))) | U7: 2% of agreed value, minimum $10,000 | V7: Agreed Value | W7: $1,000 | X7: $1,000,000 CSL | AA7: Surplus Lines | AB7: 11746.86 | AC7: 0 | AD7: =IF(ISNUMBER($AB7),$AB7*(1+N($AC7)),"") | AE7: 350 | AF7: 250 | AH7: =IF(ISNUMBER($AD7),($AD7+$AE7+$AF7)*$AG7,"") | AJ7: =IF(ISNUMBER($AD7),SUM($AD7:$AH7),"") | AK7: =IF(AND(ISNUMBER($AB7),ISNUMBER($AD7)),IF($AB7>0,$AD7/$AB7,""),"") | AL7: At technical | AM7: =IF(ISNUMBER($AD7),Header!$I$3,"") | AN7: =IF(ISNUMBER($AD7),$AO7+$AP7,"") | AO7: =IF(ISNUMBER($AD7),ROUND($AD7*Header!$K$3,2),"") | AP7: =IF(ISNUMBER($AD7),ROUND($AD7*Header!$M$3,2),"") | AQ7: =IF(ISNUMBER($AD7),ROUND($AD7,2)-$AO7-$AP7,"") | AR7: =IF(ISNUMBER($AD7),IF(Header!$D$34="","?",$AD7*Header!$D$34),"") | AS7: =IF(ISNUMBER($AB7),IF(Header!$D$34="","?",$AB7*Header!$D$34),"") | AT7: =IF(AND(ISNUMBER($AB7),$M7>0),$AB7/$M7*100,"") | AU7: =IF(AND(ISNUMBER($AD7),$M7>0),$AD7/$M7*100,"") | AV7: =IF(AND(ISNUMBER($AB7),ISNUMBER($AD7),ABS($AB7)>0),$AD7/$AB7,"") | AW7: =IF(ISNUMBER($AD7),MAX(0,(1-0.55-Header!$O$3)*Header!$Q$3*$AQ7),"") | AX7: =IF($A7="","",IF(TRIM(IF($A7="","Missing certificate ref. ","") & IF($C7="","Missing effective date. ","") & IF($D7="","Missing binding status. ","") & IF($E7="","Missing movement type. ","") & IF($I7="","Missing make. ","") & IF($L7="","Missing vehicle class. ","") & IF($M7="","Missing agreed value. ","") & IF($N7="","Missing policy type. ","") & IF($Q7="","Missing garaging state. ","") & IF($R7="","Missing garaging ZIP. ","") & IF($S7="","Missing cat zone. ","") & IF($V7="","Missing valuation basis. ","") & IF($W7="","Missing PD deductible. ","") & IF($X7="","Missing liability limit. ","") & IF($AB7="","Missing technical premium. ","") & IF($AF7="","Missing surplus lines tax %. ",""))="","PASS","FAIL: "&TRIM(IF($A7="","Missing certificate ref. ","") & IF($C7="","Missing effective date. ","") & IF($D7="","Missing binding status. ","") & IF($E7="","Missing movement type. ","") & IF($I7="","Missing make. ","") & IF($L7="","Missing vehicle class. ","") & IF($M7="","Missing agreed value. ","") & IF($N7="","Missing policy type. ","") & IF($Q7="","Missing garaging state. ","") & IF($R7="","Missing garaging ZIP. ","") & IF($S7="","Missing cat zone. ","") & IF($V7="","Missing valuation basis. ","") & IF($W7="","Missing PD deductible. ","") & IF($X7="","Missing liability limit. ","") & IF($AB7="","Missing technical premium. ","") & IF($AF7="","Missing surplus lines tax %. ","")))) | AY7: =IF($M7="","",IF(ISNUMBER($M7),IF($M7>=Header!$C$18,"YES — refer","No"),"")) | AZ7: =IF($AD7="","",IF(ISNUMBER($AD7),IF($AD7<Header!$C$20,"BELOW MIN PREMIUM","OK"),"")) | BA7: Yes | BB7: Yes | BC7: Synthetic demo data | BE7: =IF(OR($A7="",$L7="",$H7=""),"",IF(AND(LEFT($L7,2)="06",$H7>1945),"FAIL - pre-war class, year "&$H7,IF(AND(LEFT($L7,2)="07",OR($H7<1946,$H7>1972)),"FAIL - 1946-72 class, year "&$H7,IF(AND(LEFT($L7,2)="08",OR($H7<1973,$H7>1999)),"FAIL - 1973-99 class, year "&$H7,IF(AND(LEFT($L7,2)="09",OR($H7<2000,$H7>2010)),"FAIL - 2000-10 class, year "&$H7,"OK"))))) | BF7: =IF($AD7="","",IF(ROUND($AO7+$AP7+$AQ7-$AD7,2)=0,"OK","FAIL - out by "&TEXT($AO7+$AP7+$AQ7-$AD7,"$0.00")))
A8: CANON-202602-004667 | B8: Horace Vasquez | C8: 46080 | D8: Bound - within authority | E8: New business | F8: B1234EXOTIC26 | G8: =IF($A8="","",IF($C8="","",YEAR($C8))) | H8: 2012 | I8: Ferrari | J8: 296 GTB | K8: SS69EFAF6XCS4B5DY | L8: 03 - Supercar | M8: 780000 | N8: Personal | O8: Personal - regular use | P8: 2,500 - 5,000 | Q8: Rhode Island | R8: 02903 | S8: Tier 3 - Coastal wind (25-100 miles) | T8: =IF($A8="","",IF($S8="","",IFERROR(INDEX('[1]natural catastrophe'!$D$6:$D$17,MATCH($S8,'[1]natural catastrophe'!$B$6:$B$17,0)),"?"))) | U8: 2% of agreed value, minimum $10,000 | V8: Agreed Value | W8: $1,000 | X8: $1,000,000 CSL | AA8: Surplus Lines | AB8: 16840.33 | AC8: 0 | AD8: =IF(ISNUMBER($AB8),$AB8*(1+N($AC8)),"") | AE8: 350 | AF8: 0 | AH8: =IF(ISNUMBER($AD8),($AD8+$AE8+$AF8)*$AG8,"") | AJ8: =IF(ISNUMBER($AD8),SUM($AD8:$AH8),"") | AK8: =IF(AND(ISNUMBER($AB8),ISNUMBER($AD8)),IF($AB8>0,$AD8/$AB8,""),"") | AL8: At technical | AM8: =IF(ISNUMBER($AD8),Header!$I$3,"") | AN8: =IF(ISNUMBER($AD8),$AO8+$AP8,"") | AO8: =IF(ISNUMBER($AD8),ROUND($AD8*Header!$K$3,2),"") | AP8: =IF(ISNUMBER($AD8),ROUND($AD8*Header!$M$3,2),"") | AQ8: =IF(ISNUMBER($AD8),ROUND($AD8,2)-$AO8-$AP8,"") | AR8: =IF(ISNUMBER($AD8),IF(Header!$D$34="","?",$AD8*Header!$D$34),"") | AS8: =IF(ISNUMBER($AB8),IF(Header!$D$34="","?",$AB8*Header!$D$34),"") | AT8: =IF(AND(ISNUMBER($AB8),$M8>0),$AB8/$M8*100,"") | AU8: =IF(AND(ISNUMBER($AD8),$M8>0),$AD8/$M8*100,"") | AV8: =IF(AND(ISNUMBER($AB8),ISNUMBER($AD8),ABS($AB8)>0),$AD8/$AB8,"") | AW8: =IF(ISNUMBER($AD8),MAX(0,(1-0.55-Header!$O$3)*Header!$Q$3*$AQ8),"") | AX8: =IF($A8="","",IF(TRIM(IF($A8="","Missing certificate ref. ","") & IF($C8="","Missing effective date. ","") & IF($D8="","Missing binding status. ","") & IF($E8="","Missing movement type. ","") & IF($I8="","Missing make. ","") & IF($L8="","Missing vehicle class. ","") & IF($M8="","Missing agreed value. ","") & IF($N8="","Missing policy type. ","") & IF($Q8="","Missing garaging state. ","") & IF($R8="","Missing garaging ZIP. ","") & IF($S8="","Missing cat zone. ","") & IF($V8="","Missing valuation basis. ","") & IF($W8="","Missing PD deductible. ","") & IF($X8="","Missing liability limit. ","") & IF($AB8="","Missing technical premium. ","") & IF($AF8="","Missing surplus lines tax %. ",""))="","PASS","FAIL: "&TRIM(IF($A8="","Missing certificate ref. ","") & IF($C8="","Missing effective date. ","") & IF($D8="","Missing binding status. ","") & IF($E8="","Missing movement type. ","") & IF($I8="","Missing make. ","") & IF($L8="","Missing vehicle class. ","") & IF($M8="","Missing agreed value. ","") & IF($N8="","Missing policy type. ","") & IF($Q8="","Missing garaging state. ","") & IF($R8="","Missing garaging ZIP. ","") & IF($S8="","Missing cat zone. ","") & IF($V8="","Missing valuation basis. ","") & IF($W8="","Missing PD deductible. ","") & IF($X8="","Missing liability limit. ","") & IF($AB8="","Missing technical premium. ","") & IF($AF8="","Missing surplus lines tax %. ","")))) | AY8: =IF($M8="","",IF(ISNUMBER($M8),IF($M8>=Header!$C$18,"YES — refer","No"),"")) | AZ8: =IF($AD8="","",IF(ISNUMBER($AD8),IF($AD8<Header!$C$20,"BELOW MIN PREMIUM","OK"),"")) | BA8: Yes | BB8: Yes | BC8: Synthetic demo data | BE8: =IF(OR($A8="",$L8="",$H8=""),"",IF(AND(LEFT($L8,2)="06",$H8>1945),"FAIL - pre-war class, year "&$H8,IF(AND(LEFT($L8,2)="07",OR($H8<1946,$H8>1972)),"FAIL - 1946-72 class, year "&$H8,IF(AND(LEFT($L8,2)="08",OR($H8<1973,$H8>1999)),"FAIL - 1973-99 class, year "&$H8,IF(AND(LEFT($L8,2)="09",OR($H8<2000,$H8>2010)),"FAIL - 2000-10 class, year "&$H8,"OK"))))) | BF8: =IF($AD8="","",IF(ROUND($AO8+$AP8+$AQ8-$AD8,2)=0,"OK","FAIL - out by "&TEXT($AO8+$AP8+$AQ8-$AD8,"$0.00")))
A9: CANON-202602-004670 | B9: Noor Rourke | C9: 46071 | D9: Bound - within authority | E9: New business | F9: B1234EXOTIC26 | G9: =IF($A9="","",IF($C9="","",YEAR($C9))) | H9: 1990 | I9: BMW | J9: M8 Competition | K9: H4SFJJSG71GR36W0M | L9: 02 - Sports / GT | M9: 450000 | N9: Personal | O9: Personal - regular use | P9: 2,500 - 5,000 | Q9: Texas | R9: 75201 | S9: Tier 2 - Coastal wind (1-25 miles) | T9: =IF($A9="","",IF($S9="","",IFERROR(INDEX('[1]natural catastrophe'!$D$6:$D$17,MATCH($S9,'[1]natural catastrophe'!$B$6:$B$17,0)),"?"))) | U9: 2% of agreed value, minimum $10,000 | V9: Agreed Value | W9: $1,000 | X9: $1,000,000 CSL | AA9: Surplus Lines | AB9: 6438.48 | AC9: 0 | AD9: =IF(ISNUMBER($AB9),$AB9*(1+N($AC9)),"") | AE9: 350 | AF9: 0 | AH9: =IF(ISNUMBER($AD9),($AD9+$AE9+$AF9)*$AG9,"") | AJ9: =IF(ISNUMBER($AD9),SUM($AD9:$AH9),"") | AK9: =IF(AND(ISNUMBER($AB9),ISNUMBER($AD9)),IF($AB9>0,$AD9/$AB9,""),"") | AL9: At technical | AM9: =IF(ISNUMBER($AD9),Header!$I$3,"") | AN9: =IF(ISNUMBER($AD9),$AO9+$AP9,"") | AO9: =IF(ISNUMBER($AD9),ROUND($AD9*Header!$K$3,2),"") | AP9: =IF(ISNUMBER($AD9),ROUND($AD9*Header!$M$3,2),"") | AQ9: =IF(ISNUMBER($AD9),ROUND($AD9,2)-$AO9-$AP9,"") | AR9: =IF(ISNUMBER($AD9),IF(Header!$D$34="","?",$AD9*Header!$D$34),"") | AS9: =IF(ISNUMBER($AB9),IF(Header!$D$34="","?",$AB9*Header!$D$34),"") | AT9: =IF(AND(ISNUMBER($AB9),$M9>0),$AB9/$M9*100,"") | AU9: =IF(AND(ISNUMBER($AD9),$M9>0),$AD9/$M9*100,"") | AV9: =IF(AND(ISNUMBER($AB9),ISNUMBER($AD9),ABS($AB9)>0),$AD9/$AB9,"") | AW9: =IF(ISNUMBER($AD9),MAX(0,(1-0.55-Header!$O$3)*Header!$Q$3*$AQ9),"") | AX9: =IF($A9="","",IF(TRIM(IF($A9="","Missing certificate ref. ","") & IF($C9="","Missing effective date. ","") & IF($D9="","Missing binding status. ","") & IF($E9="","Missing movement type. ","") & IF($I9="","Missing make. ","") & IF($L9="","Missing vehicle class. ","") & IF($M9="","Missing agreed value. ","") & IF($N9="","Missing policy type. ","") & IF($Q9="","Missing garaging state. ","") & IF($R9="","Missing garaging ZIP. ","") & IF($S9="","Missing cat zone. ","") & IF($V9="","Missing valuation basis. ","") & IF($W9="","Missing PD deductible. ","") & IF($X9="","Missing liability limit. ","") & IF($AB9="","Missing technical premium. ","") & IF($AF9="","Missing surplus lines tax %. ",""))="","PASS","FAIL: "&TRIM(IF($A9="","Missing certificate ref. ","") & IF($C9="","Missing effective date. ","") & IF($D9="","Missing binding status. ","") & IF($E9="","Missing movement type. ","") & IF($I9="","Missing make. ","") & IF($L9="","Missing vehicle class. ","") & IF($M9="","Missing agreed value. ","") & IF($N9="","Missing policy type. ","") & IF($Q9="","Missing garaging state. ","") & IF($R9="","Missing garaging ZIP. ","") & IF($S9="","Missing cat zone. ","") & IF($V9="","Missing valuation basis. ","") & IF($W9="","Missing PD deductible. ","") & IF($X9="","Missing liability limit. ","") & IF($AB9="","Missing technical premium. ","") & IF($AF9="","Missing surplus lines tax %. ","")))) | AY9: =IF($M9="","",IF(ISNUMBER($M9),IF($M9>=Header!$C$18,"YES — refer","No"),"")) | AZ9: =IF($AD9="","",IF(ISNUMBER($AD9),IF($AD9<Header!$C$20,"BELOW MIN PREMIUM","OK"),"")) | BA9: Yes | BB9: Yes | BC9: Synthetic demo data | BE9: =IF(OR($A9="",$L9="",$H9=""),"",IF(AND(LEFT($L9,2)="06",$H9>1945),"FAIL - pre-war class, year "&$H9,IF(AND(LEFT($L9,2)="07",OR($H9<1946,$H9>1972)),"FAIL - 1946-72 class, year "&$H9,IF(AND(LEFT($L9,2)="08",OR($H9<1973,$H9>1999)),"FAIL - 1973-99 class, year "&$H9,IF(AND(LEFT($L9,2)="09",OR($H9<2000,$H9>2010)),"FAIL - 2000-10 class, year "&$H9,"OK"))))) | BF9: =IF($AD9="","",IF(ROUND($AO9+$AP9+$AQ9-$AD9,2)=0,"OK","FAIL - out by "&TEXT($AO9+$AP9+$AQ9-$AD9,"$0.00")))
A10: CANON-202602-004673 | B10: Callum Castellanos | C10: 46074 | D10: Bound - within authority | E10: New business | F10: B1234EXOTIC26 | G10: =IF($A10="","",IF($C10="","",YEAR($C10))) | H10: 1970 | I10: Bentley | J10: 4.5 Litre | K10: NR3EG7UAXLFY4NBHF | L10: 07 - Post-War Classic (1946-1972) | M10: 1250000 | N10: Personal | O10: Personal - regular use | P10: Under 1,000 | Q10: Maryland | R10: 21201 | S10: Tier 3 - Coastal wind (25-100 miles) | T10: =IF($A10="","",IF($S10="","",IFERROR(INDEX('[1]natural catastrophe'!$D$6:$D$17,MATCH($S10,'[1]natural catastrophe'!$B$6:$B$17,0)),"?"))) | U10: 2% of agreed value, minimum $10,000 | V10: Agreed Value | W10: $1,000 | X10: $1,000,000 CSL | AA10: Surplus Lines | AB10: 6697.68 | AC10: 0 | AD10: =IF(ISNUMBER($AB10),$AB10*(1+N($AC10)),"") | AE10: 350 | AF10: 250 | AH10: =IF(ISNUMBER($AD10),($AD10+$AE10+$AF10)*$AG10,"") | AJ10: =IF(ISNUMBER($AD10),SUM($AD10:$AH10),"") | AK10: =IF(AND(ISNUMBER($AB10),ISNUMBER($AD10)),IF($AB10>0,$AD10/$AB10,""),"") | AL10: At technical | AM10: =IF(ISNUMBER($AD10),Header!$I$3,"") | AN10: =IF(ISNUMBER($AD10),$AO10+$AP10,"") | AO10: =IF(ISNUMBER($AD10),ROUND($AD10*Header!$K$3,2),"") | AP10: =IF(ISNUMBER($AD10),ROUND($AD10*Header!$M$3,2),"") | AQ10: =IF(ISNUMBER($AD10),ROUND($AD10,2)-$AO10-$AP10,"") | AR10: =IF(ISNUMBER($AD10),IF(Header!$D$34="","?",$AD10*Header!$D$34),"") | AS10: =IF(ISNUMBER($AB10),IF(Header!$D$34="","?",$AB10*Header!$D$34),"") | AT10: =IF(AND(ISNUMBER($AB10),$M10>0),$AB10/$M10*100,"") | AU10: =IF(AND(ISNUMBER($AD10),$M10>0),$AD10/$M10*100,"") | AV10: =IF(AND(ISNUMBER($AB10),ISNUMBER($AD10),ABS($AB10)>0),$AD10/$AB10,"") | AW10: =IF(ISNUMBER($AD10),MAX(0,(1-0.55-Header!$O$3)*Header!$Q$3*$AQ10),"") | AX10: =IF($A10="","",IF(TRIM(IF($A10="","Missing certificate ref. ","") & IF($C10="","Missing effective date. ","") & IF($D10="","Missing binding status. ","") & IF($E10="","Missing movement type. ","") & IF($I10="","Missing make. ","") & IF($L10="","Missing vehicle class. ","") & IF($M10="","Missing agreed value. ","") & IF($N10="","Missing policy type. ","") & IF($Q10="","Missing garaging state. ","") & IF($R10="","Missing garaging ZIP. ","") & IF($S10="","Missing cat zone. ","") & IF($V10="","Missing valuation basis. ","") & IF($W10="","Missing PD deductible. ","") & IF($X10="","Missing liability limit. ","") & IF($AB10="","Missing technical premium. ","") & IF($AF10="","Missing surplus lines tax %. ",""))="","PASS","FAIL: "&TRIM(IF($A10="","Missing certificate ref. ","") & IF($C10="","Missing effective date. ","") & IF($D10="","Missing binding status. ","") & IF($E10="","Missing movement type. ","") & IF($I10="","Missing make. ","") & IF($L10="","Missing vehicle class. ","") & IF($M10="","Missing agreed value. ","") & IF($N10="","Missing policy type. ","") & IF($Q10="","Missing garaging state. ","") & IF($R10="","Missing garaging ZIP. ","") & IF($S10="","Missing cat zone. ","") & IF($V10="","Missing valuation basis. ","") & IF($W10="","Missing PD deductible. ","") & IF($X10="","Missing liability limit. ","") & IF($AB10="","Missing technical premium. ","") & IF($AF10="","Missing surplus lines tax %. ","")))) | AY10: =IF($M10="","",IF(ISNUMBER($M10),IF($M10>=Header!$C$18,"YES — refer","No"),"")) | AZ10: =IF($AD10="","",IF(ISNUMBER($AD10),IF($AD10<Header!$C$20,"BELOW MIN PREMIUM","OK"),"")) | BA10: Yes | BB10: Yes | BC10: Synthetic demo data | BE10: =IF(OR($A10="",$L10="",$H10=""),"",IF(AND(LEFT($L10,2)="06",$H10>1945),"FAIL - pre-war class, year "&$H10,IF(AND(LEFT($L10,2)="07",OR($H10<1946,$H10>1972)),"FAIL - 1946-72 class, year "&$H10,IF(AND(LEFT($L10,2)="08",OR($H10<1973,$H10>1999)),"FAIL - 1973-99 class, year "&$H10,IF(AND(LEFT($L10,2)="09",OR($H10<2000,$H10>2010)),"FAIL - 2000-10 class, year "&$H10,"OK"))))) | BF10: =IF($AD10="","",IF(ROUND($AO10+$AP10+$AQ10-$AD10,2)=0,"OK","FAIL - out by "&TEXT($AO10+$AP10+$AQ10-$AD10,"$0.00")))
A11: CANON-202602-004675 | B11: Callum Merriweather | C11: 46079 | D11: Bound - within authority | E11: New business | F11: B1234EXOTIC26 | G11: =IF($A11="","",IF($C11="","",YEAR($C11))) | H11: 2016 | I11: McLaren | J11: 750S | K11: KY9XFAE93K3VN58WG | L11: 03 - Supercar | M11: 985000 | N11: Personal | O11: Personal - regular use | P11: 1,000 - 2,500 | Q11: Illinois | R11: 60601 | S11: Severe convective - hail / tornado (moderate) | T11: =IF($A11="","",IF($S11="","",IFERROR(INDEX('[1]natural catastrophe'!$D$6:$D$17,MATCH($S11,'[1]natural catastrophe'!$B$6:$B$17,0)),"?"))) | U11: $5,000 | V11: Agreed Value | W11: $1,000 | X11: $1,000,000 CSL | AA11: Surplus Lines | AB11: 21111.09 | AC11: 0 | AD11: =IF(ISNUMBER($AB11),$AB11*(1+N($AC11)),"") | AE11: 350 | AF11: 0 | AH11: =IF(ISNUMBER($AD11),($AD11+$AE11+$AF11)*$AG11,"") | AJ11: =IF(ISNUMBER($AD11),SUM($AD11:$AH11),"") | AK11: =IF(AND(ISNUMBER($AB11),ISNUMBER($AD11)),IF($AB11>0,$AD11/$AB11,""),"") | AL11: At technical | AM11: =IF(ISNUMBER($AD11),Header!$I$3,"") | AN11: =IF(ISNUMBER($AD11),$AO11+$AP11,"") | AO11: =IF(ISNUMBER($AD11),ROUND($AD11*Header!$K$3,2),"") | AP11: =IF(ISNUMBER($AD11),ROUND($AD11*Header!$M$3,2),"") | AQ11: =IF(ISNUMBER($AD11),ROUND($AD11,2)-$AO11-$AP11,"") | AR11: =IF(ISNUMBER($AD11),IF(Header!$D$34="","?",$AD11*Header!$D$34),"") | AS11: =IF(ISNUMBER($AB11),IF(Header!$D$34="","?",$AB11*Header!$D$34),"") | AT11: =IF(AND(ISNUMBER($AB11),$M11>0),$AB11/$M11*100,"") | AU11: =IF(AND(ISNUMBER($AD11),$M11>0),$AD11/$M11*100,"") | AV11: =IF(AND(ISNUMBER($AB11),ISNUMBER($AD11),ABS($AB11)>0),$AD11/$AB11,"") | AW11: =IF(ISNUMBER($AD11),MAX(0,(1-0.55-Header!$O$3)*Header!$Q$3*$AQ11),"") | AX11: =IF($A11="","",IF(TRIM(IF($A11="","Missing certificate ref. ","") & IF($C11="","Missing effective date. ","") & IF($D11="","Missing binding status. ","") & IF($E11="","Missing movement type. ","") & IF($I11="","Missing make. ","") & IF($L11="","Missing vehicle class. ","") & IF($M11="","Missing agreed value. ","") & IF($N11="","Missing policy type. ","") & IF($Q11="","Missing garaging state. ","") & IF($R11="","Missing garaging ZIP. ","") & IF($S11="","Missing cat zone. ","") & IF($V11="","Missing valuation basis. ","") & IF($W11="","Missing PD deductible. ","") & IF($X11="","Missing liability limit. ","") & IF($AB11="","Missing technical premium. ","") & IF($AF11="","Missing surplus lines tax %. ",""))="","PASS","FAIL: "&TRIM(IF($A11="","Missing certificate ref. ","") & IF($C11="","Missing effective date. ","") & IF($D11="","Missing binding status. ","") & IF($E11="","Missing movement type. ","") & IF($I11="","Missing make. ","") & IF($L11="","Missing vehicle class. ","") & IF($M11="","Missing agreed value. ","") & IF($N11="","Missing policy type. ","") & IF($Q11="","Missing garaging state. ","") & IF($R11="","Missing garaging ZIP. ","") & IF($S11="","Missing cat zone. ","") & IF($V11="","Missing valuation basis. ","") & IF($W11="","Missing PD deductible. ","") & IF($X11="","Missing liability limit. ","") & IF($AB11="","Missing technical premium. ","") & IF($AF11="","Missing surplus lines tax %. ","")))) | AY11: =IF($M11="","",IF(ISNUMBER($M11),IF($M11>=Header!$C$18,"YES — refer","No"),"")) | AZ11: =IF($AD11="","",IF(ISNUMBER($AD11),IF($AD11<Header!$C$20,"BELOW MIN PREMIUM","OK"),"")) | BA11: Yes | BB11: Yes | BC11: Synthetic demo data | BE11: =IF(OR($A11="",$L11="",$H11=""),"",IF(AND(LEFT($L11,2)="06",$H11>1945),"FAIL - pre-war class, year "&$H11,IF(AND(LEFT($L11,2)="07",OR($H11<1946,$H11>1972)),"FAIL - 1946-72 class, year "&$H11,IF(AND(LEFT($L11,2)="08",OR($H11<1973,$H11>1999)),"FAIL - 1973-99 class, year "&$H11,IF(AND(LEFT($L11,2)="09",OR($H11<2000,$H11>2010)),"FAIL - 2000-10 class, year "&$H11,"OK"))))) | BF11: =IF($AD11="","",IF(ROUND($AO11+$AP11+$AQ11-$AD11,2)=0,"OK","FAIL - out by "&TEXT($AO11+$AP11+$AQ11-$AD11,"$0.00")))
A12: CANON-202602-004676 | B12: Ramona Farkas | C12: 46067 | D12: Bound - within authority | E12: New business | F12: B1234EXOTIC26 | G12: =IF($A12="","",IF($C12="","",YEAR($C12))) | H12: 1974 | I12: Aston Martin | J12: DB12 | K12: 9EA5ZCJXL8MBT5T6Z | L12: 02 - Sports / GT | M12: 670000 | N12: Personal | O12: Personal - regular use | P12: 1,000 - 2,500 | Q12: New Jersey | R12: 07102 | S12: Tier 3 - Coastal wind (25-100 miles) | T12: =IF($A12="","",IF($S12="","",IFERROR(INDEX('[1]natural catastrophe'!$D$6:$D$17,MATCH($S12,'[1]natural catastrophe'!$B$6:$B$17,0)),"?"))) | U12: 2% of agreed value, minimum $10,000 | V12: Agreed Value | W12: $1,000 | X12: $1,000,000 CSL | AA12: Surplus Lines | AB12: 6574.17 | AC12: 0 | AD12: =IF(ISNUMBER($AB12),$AB12*(1+N($AC12)),"") | AE12: 350 | AF12: 0 | AH12: =IF(ISNUMBER($AD12),($AD12+$AE12+$AF12)*$AG12,"") | AJ12: =IF(ISNUMBER($AD12),SUM($AD12:$AH12),"") | AK12: =IF(AND(ISNUMBER($AB12),ISNUMBER($AD12)),IF($AB12>0,$AD12/$AB12,""),"") | AL12: At technical | AM12: =IF(ISNUMBER($AD12),Header!$I$3,"") | AN12: =IF(ISNUMBER($AD12),$AO12+$AP12,"") | AO12: =IF(ISNUMBER($AD12),ROUND($AD12*Header!$K$3,2),"") | AP12: =IF(ISNUMBER($AD12),ROUND($AD12*Header!$M$3,2),"") | AQ12: =IF(ISNUMBER($AD12),ROUND($AD12,2)-$AO12-$AP12,"") | AR12: =IF(ISNUMBER($AD12),IF(Header!$D$34="","?",$AD12*Header!$D$34),"") | AS12: =IF(ISNUMBER($AB12),IF(Header!$D$34="","?",$AB12*Header!$D$34),"") | AT12: =IF(AND(ISNUMBER($AB12),$M12>0),$AB12/$M12*100,"") | AU12: =IF(AND(ISNUMBER($AD12),$M12>0),$AD12/$M12*100,"") | AV12: =IF(AND(ISNUMBER($AB12),ISNUMBER($AD12),ABS($AB12)>0),$AD12/$AB12,"") | AW12: =IF(ISNUMBER($AD12),MAX(0,(1-0.55-Header!$O$3)*Header!$Q$3*$AQ12),"") | AX12: =IF($A12="","",IF(TRIM(IF($A12="","Missing certificate ref. ","") & IF($C12="","Missing effective date. ","") & IF($D12="","Missing binding status. ","") & IF($E12="","Missing movement type. ","") & IF($I12="","Missing make. ","") & IF($L12="","Missing vehicle class. ","") & IF($M12="","Missing agreed value. ","") & IF($N12="","Missing policy type. ","") & IF($Q12="","Missing garaging state. ","") & IF($R12="","Missing garaging ZIP. ","") & IF($S12="","Missing cat zone. ","") & IF($V12="","Missing valuation basis. ","") & IF($W12="","Missing PD deductible. ","") & IF($X12="","Missing liability limit. ","") & IF($AB12="","Missing technical premium. ","") & IF($AF12="","Missing surplus lines tax %. ",""))="","PASS","FAIL: "&TRIM(IF($A12="","Missing certificate ref. ","") & IF($C12="","Missing effective date. ","") & IF($D12="","Missing binding status. ","") & IF($E12="","Missing movement type. ","") & IF($I12="","Missing make. ","") & IF($L12="","Missing vehicle class. ","") & IF($M12="","Missing agreed value. ","") & IF($N12="","Missing policy type. ","") & IF($Q12="","Missing garaging state. ","") & IF($R12="","Missing garaging ZIP. ","") & IF($S12="","Missing cat zone. ","") & IF($V12="","Missing valuation basis. ","") & IF($W12="","Missing PD deductible. ","") & IF($X12="","Missing liability limit. ","") & IF($AB12="","Missing technical premium. ","") & IF($AF12="","Missing surplus lines tax %. ","")))) | AY12: =IF($M12="","",IF(ISNUMBER($M12),IF($M12>=Header!$C$18,"YES — refer","No"),"")) | AZ12: =IF($AD12="","",IF(ISNUMBER($AD12),IF($AD12<Header!$C$20,"BELOW MIN PREMIUM","OK"),"")) | BA12: Yes | BB12: Yes | BC12: Synthetic demo data | BE12: =IF(OR($A12="",$L12="",$H12=""),"",IF(AND(LEFT($L12,2)="06",$H12>1945),"FAIL - pre-war class, year "&$H12,IF(AND(LEFT($L12,2)="07",OR($H12<1946,$H12>1972)),"FAIL - 1946-72 class, year "&$H12,IF(AND(LEFT($L12,2)="08",OR($H12<1973,$H12>1999)),"FAIL - 1973-99 class, year "&$H12,IF(AND(LEFT($L12,2)="09",OR($H12<2000,$H12>2010)),"FAIL - 2000-10 class, year "&$H12,"OK"))))) | BF12: =IF($AD12="","",IF(ROUND($AO12+$AP12+$AQ12-$AD12,2)=0,"OK","FAIL - out by "&TEXT($AO12+$AP12+$AQ12-$AD12,"$0.00")))
A13: CANON-202602-004677 | B13: Mireille Kingsford | C13: 46075 | D13: Bound - within authority | E13: New business | F13: B1234EXOTIC26 | G13: =IF($A13="","",IF($C13="","",YEAR($C13))) | H13: 2019 | I13: Aston Martin | J13: DB5 | K13: W34P8EBD49W8JKPVF | L13: 02 - Sports / GT | M13: 715000 | N13: Personal | O13: Personal - regular use | P13: Under 1,000 | Q13: Texas | R13: 75201 | S13: Tier 2 - Coastal wind (1-25 miles) | T13: =IF($A13="","",IF($S13="","",IFERROR(INDEX('[1]natural catastrophe'!$D$6:$D$17,MATCH($S13,'[1]natural catastrophe'!$B$6:$B$17,0)),"?"))) | U13: 2% of agreed value, minimum $10,000 | V13: Agreed Value | W13: $1,000 | X13: $1,000,000 CSL | AA13: Surplus Lines | AB13: 5865.21 | AC13: 0 | AD13: =IF(ISNUMBER($AB13),$AB13*(1+N($AC13)),"") | AE13: 350 | AF13: 0 | AH13: =IF(ISNUMBER($AD13),($AD13+$AE13+$AF13)*$AG13,"") | AJ13: =IF(ISNUMBER($AD13),SUM($AD13:$AH13),"") | AK13: =IF(AND(ISNUMBER($AB13),ISNUMBER($AD13)),IF($AB13>0,$AD13/$AB13,""),"") | AL13: At technical | AM13: =IF(ISNUMBER($AD13),Header!$I$3,"") | AN13: =IF(ISNUMBER($AD13),$AO13+$AP13,"") | AO13: =IF(ISNUMBER($AD13),ROUND($AD13*Header!$K$3,2),"") | AP13: =IF(ISNUMBER($AD13),ROUND($AD13*Header!$M$3,2),"") | AQ13: =IF(ISNUMBER($AD13),ROUND($AD13,2)-$AO13-$AP13,"") | AR13: =IF(ISNUMBER($AD13),IF(Header!$D$34="","?",$AD13*Header!$D$34),"") | AS13: =IF(ISNUMBER($AB13),IF(Header!$D$34="","?",$AB13*Header!$D$34),"") | AT13: =IF(AND(ISNUMBER($AB13),$M13>0),$AB13/$M13*100,"") | AU13: =IF(AND(ISNUMBER($AD13),$M13>0),$AD13/$M13*100,"") | AV13: =IF(AND(ISNUMBER($AB13),ISNUMBER($AD13),ABS($AB13)>0),$AD13/$AB13,"") | AW13: =IF(ISNUMBER($AD13),MAX(0,(1-0.55-Header!$O$3)*Header!$Q$3*$AQ13),"") | AX13: =IF($A13="","",IF(TRIM(IF($A13="","Missing certificate ref. ","") & IF($C13="","Missing effective date. ","") & IF($D13="","Missing binding status. ","") & IF($E13="","Missing movement type. ","") & IF($I13="","Missing make. ","") & IF($L13="","Missing vehicle class. ","") & IF($M13="","Missing agreed value. ","") & IF($N13="","Missing policy type. ","") & IF($Q13="","Missing garaging state. ","") & IF($R13="","Missing garaging ZIP. ","") & IF($S13="","Missing cat zone. ","") & IF($V13="","Missing valuation basis. ","") & IF($W13="","Missing PD deductible. ","") & IF($X13="","Missing liability limit. ","") & IF($AB13="","Missing technical premium. ","") & IF($AF13="","Missing surplus lines tax %. ",""))="","PASS","FAIL: "&TRIM(IF($A13="","Missing certificate ref. ","") & IF($C13="","Missing effective date. ","") & IF($D13="","Missing binding status. ","") & IF($E13="","Missing movement type. ","") & IF($I13="","Missing make. ","") & IF($L13="","Missing vehicle class. ","") & IF($M13="","Missing agreed value. ","") & IF($N13="","Missing policy type. ","") & IF($Q13="","Missing garaging state. ","") & IF($R13="","Missing garaging ZIP. ","") & IF($S13="","Missing cat zone. ","") & IF($V13="","Missing valuation basis. ","") & IF($W13="","Missing PD deductible. ","") & IF($X13="","Missing liability limit. ","") & IF($AB13="","Missing technical premium. ","") & IF($AF13="","Missing surplus lines tax %. ","")))) | AY13: =IF($M13="","",IF(ISNUMBER($M13),IF($M13>=Header!$C$18,"YES — refer","No"),"")) | AZ13: =IF($AD13="","",IF(ISNUMBER($AD13),IF($AD13<Header!$C$20,"BELOW MIN PREMIUM","OK"),"")) | BA13: Yes | BB13: Yes | BC13: Synthetic demo data | BE13: =IF(OR($A13="",$L13="",$H13=""),"",IF(AND(LEFT($L13,2)="06",$H13>1945),"FAIL - pre-war class, year "&$H13,IF(AND(LEFT($L13,2)="07",OR($H13<1946,$H13>1972)),"FAIL - 1946-72 class, year "&$H13,IF(AND(LEFT($L13,2)="08",OR($H13<1973,$H13>1999)),"FAIL - 1973-99 class, year "&$H13,IF(AND(LEFT($L13,2)="09",OR($H13<2000,$H13>2010)),"FAIL - 2000-10 class, year "&$H13,"OK"))))) | BF13: =IF($AD13="","",IF(ROUND($AO13+$AP13+$AQ13-$AD13,2)=0,"OK","FAIL - out by "&TEXT($AO13+$AP13+$AQ13-$AD13,"$0.00")))
A14: CANON-202602-004678 | B14: Fitzgerald Harrington | C14: 46072 | D14: Bound - within authority | E14: New business | F14: B1234EXOTIC26 | G14: =IF($A14="","",IF($C14="","",YEAR($C14))) | H14: 2011 | I14: Bentley | J14: Continental GT | K14: 7GZTAVW92GLS0HRPY | L14: 02 - Sports / GT | M14: 210000 | N14: Personal | O14: Personal - regular use | P14: Under 1,000 | Q14: Alabama | R14: 35203 | S14: Tier 2 - Coastal wind (1-25 miles) | T14: =IF($A14="","",IF($S14="","",IFERROR(INDEX('[1]natural catastrophe'!$D$6:$D$17,MATCH($S14,'[1]natural catastrophe'!$B$6:$B$17,0)),"?"))) | U14: 2% of agreed value, minimum $10,000 | V14: Agreed Value | W14: $1,000 | X14: $1,000,000 CSL | AA14: Surplus Lines | AB14: 4070.27 | AC14: 0 | AD14: =IF(ISNUMBER($AB14),$AB14*(1+N($AC14)),"") | AE14: 350 | AF14: 0 | AH14: =IF(ISNUMBER($AD14),($AD14+$AE14+$AF14)*$AG14,"") | AJ14: =IF(ISNUMBER($AD14),SUM($AD14:$AH14),"") | AK14: =IF(AND(ISNUMBER($AB14),ISNUMBER($AD14)),IF($AB14>0,$AD14/$AB14,""),"") | AL14: At technical | AM14: =IF(ISNUMBER($AD14),Header!$I$3,"") | AN14: =IF(ISNUMBER($AD14),$AO14+$AP14,"") | AO14: =IF(ISNUMBER($AD14),ROUND($AD14*Header!$K$3,2),"") | AP14: =IF(ISNUMBER($AD14),ROUND($AD14*Header!$M$3,2),"") | AQ14: =IF(ISNUMBER($AD14),ROUND($AD14,2)-$AO14-$AP14,"") | AR14: =IF(ISNUMBER($AD14),IF(Header!$D$34="","?",$AD14*Header!$D$34),"") | AS14: =IF(ISNUMBER($AB14),IF(Header!$D$34="","?",$AB14*Header!$D$34),"") | AT14: =IF(AND(ISNUMBER($AB14),$M14>0),$AB14/$M14*100,"") | AU14: =IF(AND(ISNUMBER($AD14),$M14>0),$AD14/$M14*100,"") | AV14: =IF(AND(ISNUMBER($AB14),ISNUMBER($AD14),ABS($AB14)>0),$AD14/$AB14,"") | AW14: =IF(ISNUMBER($AD14),MAX(0,(1-0.55-Header!$O$3)*Header!$Q$3*$AQ14),"") | AX14: =IF($A14="","",IF(TRIM(IF($A14="","Missing certificate ref. ","") & IF($C14="","Missing effective date. ","") & IF($D14="","Missing binding status. ","") & IF($E14="","Missing movement type. ","") & IF($I14="","Missing make. ","") & IF($L14="","Missing vehicle class. ","") & IF($M14="","Missing agreed value. ","") & IF($N14="","Missing policy type. ","") & IF($Q14="","Missing garaging state. ","") & IF($R14="","Missing garaging ZIP. ","") & IF($S14="","Missing cat zone. ","") & IF($V14="","Missing valuation basis. ","") & IF($W14="","Missing PD deductible. ","") & IF($X14="","Missing liability limit. ","") & IF($AB14="","Missing technical premium. ","") & IF($AF14="","Missing surplus lines tax %. ",""))="","PASS","FAIL: "&TRIM(IF($A14="","Missing certificate ref. ","") & IF($C14="","Missing effective date. ","") & IF($D14="","Missing binding status. ","") & IF($E14="","Missing movement type. ","") & IF($I14="","Missing make. ","") & IF($L14="","Missing vehicle class. ","") & IF($M14="","Missing agreed value. ","") & IF($N14="","Missing policy type. ","") & IF($Q14="","Missing garaging state. ","") & IF($R14="","Missing garaging ZIP. ","") & IF($S14="","Missing cat zone. ","") & IF($V14="","Missing valuation basis. ","") & IF($W14="","Missing PD deductible. ","") & IF($X14="","Missing liability limit. ","") & IF($AB14="","Missing technical premium. ","") & IF($AF14="","Missing surplus lines tax %. ","")))) | AY14: =IF($M14="","",IF(ISNUMBER($M14),IF($M14>=Header!$C$18,"YES — refer","No"),"")) | AZ14: =IF($AD14="","",IF(ISNUMBER($AD14),IF($AD14<Header!$C$20,"BELOW MIN PREMIUM","OK"),"")) | BA14: Yes | BB14: Yes | BC14: Synthetic demo data | BE14: =IF(OR($A14="",$L14="",$H14=""),"",IF(AND(LEFT($L14,2)="06",$H14>1945),"FAIL - pre-war class, year "&$H14,IF(AND(LEFT($L14,2)="07",OR($H14<1946,$H14>1972)),"FAIL - 1946-72 class, year "&$H14,IF(AND(LEFT($L14,2)="08",OR($H14<1973,$H14>1999)),"FAIL - 1973-99 class, year "&$H14,IF(AND(LEFT($L14,2)="09",OR($H14<2000,$H14>2010)),"FAIL - 2000-10 class, year "&$H14,"OK"))))) | BF14: =IF($AD14="","",IF(ROUND($AO14+$AP14+$AQ14-$AD14,2)=0,"OK","FAIL - out by "&TEXT($AO14+$AP14+$AQ14-$AD14,"$0.00")))
A15: CANON-202602-004681 | B15: Ottilie Pennington | C15: 46056 | D15: Bound - within authority | E15: New business | F15: B1234EXOTIC26 | G15: =IF($A15="","",IF($C15="","",YEAR($C15))) | H15: 1979 | I15: Porsche | J15: 911 Turbo S | K15: F7M0Z50FFX1D3U0AV | L15: 02 - Sports / GT | M15: 1250000 | N15: Personal | O15: Personal - regular use | P15: Under 1,000 | Q15: North Carolina | R15: 28202 | S15: Tier 2 - Coastal wind (1-25 miles) | T15: =IF($A15="","",IF($S15="","",IFERROR(INDEX('[1]natural catastrophe'!$D$6:$D$17,MATCH($S15,'[1]natural catastrophe'!$B$6:$B$17,0)),"?"))) | U15: 2% of agreed value, minimum $10,000 | V15: Agreed Value | W15: $1,000 | X15: $1,000,000 CSL | AA15: Surplus Lines | AB15: 13115.42 | AC15: 0 | AD15: =IF(ISNUMBER($AB15),$AB15*(1+N($AC15)),"") | AE15: 350 | AF15: 250 | AH15: =IF(ISNUMBER($AD15),($AD15+$AE15+$AF15)*$AG15,"") | AJ15: =IF(ISNUMBER($AD15),SUM($AD15:$AH15),"") | AK15: =IF(AND(ISNUMBER($AB15),ISNUMBER($AD15)),IF($AB15>0,$AD15/$AB15,""),"") | AL15: At technical | AM15: =IF(ISNUMBER($AD15),Header!$I$3,"") | AN15: =IF(ISNUMBER($AD15),$AO15+$AP15,"") | AO15: =IF(ISNUMBER($AD15),ROUND($AD15*Header!$K$3,2),"") | AP15: =IF(ISNUMBER($AD15),ROUND($AD15*Header!$M$3,2),"") | AQ15: =IF(ISNUMBER($AD15),ROUND($AD15,2)-$AO15-$AP15,"") | AR15: =IF(ISNUMBER($AD15),IF(Header!$D$34="","?",$AD15*Header!$D$34),"") | AS15: =IF(ISNUMBER($AB15),IF(Header!$D$34="","?",$AB15*Header!$D$34),"") | AT15: =IF(AND(ISNUMBER($AB15),$M15>0),$AB15/$M15*100,"") | AU15: =IF(AND(ISNUMBER($AD15),$M15>0),$AD15/$M15*100,"") | AV15: =IF(AND(ISNUMBER($AB15),ISNUMBER($AD15),ABS($AB15)>0),$AD15/$AB15,"") | AW15: =IF(ISNUMBER($AD15),MAX(0,(1-0.55-Header!$O$3)*Header!$Q$3*$AQ15),"") | AX15: =IF($A15="","",IF(TRIM(IF($A15="","Missing certificate ref. ","") & IF($C15="","Missing effective date. ","") & IF($D15="","Missing binding status. ","") & IF($E15="","Missing movement type. ","") & IF($I15="","Missing make. ","") & IF($L15="","Missing vehicle class. ","") & IF($M15="","Missing agreed value. ","") & IF($N15="","Missing policy type. ","") & IF($Q15="","Missing garaging state. ","") & IF($R15="","Missing garaging ZIP. ","") & IF($S15="","Missing cat zone. ","") & IF($V15="","Missing valuation basis. ","") & IF($W15="","Missing PD deductible. ","") & IF($X15="","Missing liability limit. ","") & IF($AB15="","Missing technical premium. ","") & IF($AF15="","Missing surplus lines tax %. ",""))="","PASS","FAIL: "&TRIM(IF($A15="","Missing certificate ref. ","") & IF($C15="","Missing effective date. ","") & IF($D15="","Missing binding status. ","") & IF($E15="","Missing movement type. ","") & IF($I15="","Missing make. ","") & IF($L15="","Missing vehicle class. ","") & IF($M15="","Missing agreed value. ","") & IF($N15="","Missing policy type. ","") & IF($Q15="","Missing garaging state. ","") & IF($R15="","Missing garaging ZIP. ","") & IF($S15="","Missing cat zone. ","") & IF($V15="","Missing valuation basis. ","") & IF($W15="","Missing PD deductible. ","") & IF($X15="","Missing liability limit. ","") & IF($AB15="","Missing technical premium. ","") & IF($AF15="","Missing surplus lines tax %. ","")))) | AY15: =IF($M15="","",IF(ISNUMBER($M15),IF($M15>=Header!$C$18,"YES — refer","No"),"")) | AZ15: =IF($AD15="","",IF(ISNUMBER($AD15),IF($AD15<Header!$C$20,"BELOW MIN PREMIUM","OK"),"")) | BA15: Yes | BB15: Yes | BC15: Synthetic demo data | BE15: =IF(OR($A15="",$L15="",$H15=""),"",IF(AND(LEFT($L15,2)="06",$H15>1945),"FAIL - pre-war class, year "&$H15,IF(AND(LEFT($L15,2)="07",OR($H15<1946,$H15>1972)),"FAIL - 1946-72 class, year "&$H15,IF(AND(LEFT($L15,2)="08",OR($H15<1973,$H15>1999)),"FAIL - 1973-99 class, year "&$H15,IF(AND(LEFT($L15,2)="09",OR($H15<2000,$H15>2010)),"FAIL - 2000-10 class, year "&$H15,"OK"))))) | BF15: =IF($AD15="","",IF(ROUND($AO15+$AP15+$AQ15-$AD15,2)=0,"OK","FAIL - out by "&TEXT($AO15+$AP15+$AQ15-$AD15,"$0.00")))
A16: CANON-202602-004684 | B16: Ottilie Nakashima | C16: 46056 | D16: Bound - within authority | E16: New business | F16: B1234EXOTIC26 | G16: =IF($A16="","",IF($C16="","",YEAR($C16))) | H16: 1961 | I16: Maserati | J16: GranTurismo | K16: BPPT0RA6459G9ZLN5 | L16: 02 - Sports / GT | M16: 315000 | N16: Personal | O16: Personal - regular use | P16: 1,000 - 2,500 | Q16: Illinois | R16: 60601 | S16: Severe convective - hail / tornado (moderate) | T16: =IF($A16="","",IF($S16="","",IFERROR(INDEX('[1]natural catastrophe'!$D$6:$D$17,MATCH($S16,'[1]natural catastrophe'!$B$6:$B$17,0)),"?"))) | U16: $5,000 | V16: Agreed Value | W16: $1,000 | X16: $1,000,000 CSL | AA16: Surplus Lines | AB16: 5329.94 | AC16: 0 | AD16: =IF(ISNUMBER($AB16),$AB16*(1+N($AC16)),"") | AE16: 350 | AF16: 0 | AH16: =IF(ISNUMBER($AD16),($AD16+$AE16+$AF16)*$AG16,"") | AJ16: =IF(ISNUMBER($AD16),SUM($AD16:$AH16),"") | AK16: =IF(AND(ISNUMBER($AB16),ISNUMBER($AD16)),IF($AB16>0,$AD16/$AB16,""),"") | AL16: At technical | AM16: =IF(ISNUMBER($AD16),Header!$I$3,"") | AN16: =IF(ISNUMBER($AD16),$AO16+$AP16,"") | AO16: =IF(ISNUMBER($AD16),ROUND($AD16*Header!$K$3,2),"") | AP16: =IF(ISNUMBER($AD16),ROUND($AD16*Header!$M$3,2),"") | AQ16: =IF(ISNUMBER($AD16),ROUND($AD16,2)-$AO16-$AP16,"") | AR16: =IF(ISNUMBER($AD16),IF(Header!$D$34="","?",$AD16*Header!$D$34),"") | AS16: =IF(ISNUMBER($AB16),IF(Header!$D$34="","?",$AB16*Header!$D$34),"") | AT16: =IF(AND(ISNUMBER($AB16),$M16>0),$AB16/$M16*100,"") | AU16: =IF(AND(ISNUMBER($AD16),$M16>0),$AD16/$M16*100,"") | AV16: =IF(AND(ISNUMBER($AB16),ISNUMBER($AD16),ABS($AB16)>0),$AD16/$AB16,"") | AW16: =IF(ISNUMBER($AD16),MAX(0,(1-0.55-Header!$O$3)*Header!$Q$3*$AQ16),"") | AX16: =IF($A16="","",IF(TRIM(IF($A16="","Missing certificate ref. ","") & IF($C16="","Missing effective date. ","") & IF($D16="","Missing binding status. ","") & IF($E16="","Missing movement type. ","") & IF($I16="","Missing make. ","") & IF($L16="","Missing vehicle class. ","") & IF($M16="","Missing agreed value. ","") & IF($N16="","Missing policy type. ","") & IF($Q16="","Missing garaging state. ","") & IF($R16="","Missing garaging ZIP. ","") & IF($S16="","Missing cat zone. ","") & IF($V16="","Missing valuation basis. ","") & IF($W16="","Missing PD deductible. ","") & IF($X16="","Missing liability limit. ","") & IF($AB16="","Missing technical premium. ","") & IF($AF16="","Missing surplus lines tax %. ",""))="","PASS","FAIL: "&TRIM(IF($A16="","Missing certificate ref. ","") & IF($C16="","Missing effective date. ","") & IF($D16="","Missing binding status. ","") & IF($E16="","Missing movement type. ","") & IF($I16="","Missing make. ","") & IF($L16="","Missing vehicle class. ","") & IF($M16="","Missing agreed value. ","") & IF($N16="","Missing policy type. ","") & IF($Q16="","Missing garaging state. ","") & IF($R16="","Missing garaging ZIP. ","") & IF($S16="","Missing cat zone. ","") & IF($V16="","Missing valuation basis. ","") & IF($W16="","Missing PD deductible. ","") & IF($X16="","Missing liability limit. ","") & IF($AB16="","Missing technical premium. ","") & IF($AF16="","Missing surplus lines tax %. ","")))) | AY16: =IF($M16="","",IF(ISNUMBER($M16),IF($M16>=Header!$C$18,"YES — refer","No"),"")) | AZ16: =IF($AD16="","",IF(ISNUMBER($AD16),IF($AD16<Header!$C$20,"BELOW MIN PREMIUM","OK"),"")) | BA16: Yes | BB16: Yes | BC16: Synthetic demo data | BE16: =IF(OR($A16="",$L16="",$H16=""),"",IF(AND(LEFT($L16,2)="06",$H16>1945),"FAIL - pre-war class, year "&$H16,IF(AND(LEFT($L16,2)="07",OR($H16<1946,$H16>1972)),"FAIL - 1946-72 class, year "&$H16,IF(AND(LEFT($L16,2)="08",OR($H16<1973,$H16>1999)),"FAIL - 1973-99 class, year "&$H16,IF(AND(LEFT($L16,2)="09",OR($H16<2000,$H16>2010)),"FAIL - 2000-10 class, year "&$H16,"OK"))))) | BF16: =IF($AD16="","",IF(ROUND($AO16+$AP16+$AQ16-$AD16,2)=0,"OK","FAIL - out by "&TEXT($AO16+$AP16+$AQ16-$AD16,"$0.00")))
... A662: CANON-202602-005556 | B662: Marisol Thistlewood | C662: 46068 | D662: Bound - within authority | E662: New business | F662: B1234EXOTIC26 | G662: =IF($A662="","",IF($C662="","",YEAR($C662))) | H662: 1958 | I662: Porsche | J662: 911 Turbo S | K662: LSZ3BGNHNH07XZR9K | L662: 02 - Sports / GT | M662: 1020000 | N662: Personal | O662: Personal - regular use | P662: 2,500 - 5,000 | Q662: Colorado | R662: 80202 | S662: Severe convective - hail alley (high) | T662: =IF($A662="","",IF($S662="","",IFERROR(INDEX('[1]natural catastrophe'!$D$6:$D$17,MATCH($S662,'[1]natural catastrophe'!$B$6:$B$17,0)),"?"))) | U662: $5,000 | V662: Agreed Value | W662: $1,000 | X662: $1,000,000 CSL | AA662: Surplus Lines | AB662: 10236.88 | AC662: 0 | AD662: =IF(ISNUMBER($AB662),$AB662*(1+N($AC662)),"") | AE662: 350 | AF662: 250 | AH662: =IF(ISNUMBER($AD662),($AD662+$AE662+$AF662)*$AG662,"") | AJ662: =IF(ISNUMBER($AD662),SUM($AD662:$AH662),"") | AK662: =IF(AND(ISNUMBER($AB662),ISNUMBER($AD662)),IF($AB662>0,$AD662/$AB662,""),"") | AL662: At technical | AM662: =IF(ISNUMBER($AD662),Header!$I$3,"") | AN662: =IF(ISNUMBER($AD662),$AO662+$AP662,"") | AO662: =IF(ISNUMBER($AD662),ROUND($AD662*Header!$K$3,2),"") | AP662: =IF(ISNUMBER($AD662),ROUND($AD662*Header!$M$3,2),"") | AQ662: =IF(ISNUMBER($AD662),ROUND($AD662,2)-$AO662-$AP662,"") | AR662: =IF(ISNUMBER($AD662),IF(Header!$D$34="","?",$AD662*Header!$D$34),"") | AS662: =IF(ISNUMBER($AB662),IF(Header!$D$34="","?",$AB662*Header!$D$34),"") | AT662: =IF(AND(ISNUMBER($AB662),$M662>0),$AB662/$M662*100,"") | AU662: =IF(AND(ISNUMBER($AD662),$M662>0),$AD662/$M662*100,"") | AV662: =IF(AND(ISNUMBER($AB662),ISNUMBER($AD662),ABS($AB662)>0),$AD662/$AB662,"") | AW662: =IF(ISNUMBER($AD662),MAX(0,(1-0.55-Header!$O$3)*Header!$Q$3*$AQ662),"") | AX662: =IF($A662="","",IF(TRIM(IF($A662="","Missing certificate ref. ","") & IF($C662="","Missing effective date. ","") & IF($D662="","Missing binding status. ","") & IF($E662="","Missing movement type. ","") & IF($I662="","Missing make. ","") & IF($L662="","Missing vehicle class. ","") & IF($M662="","Missing agreed value. ","") & IF($N662="","Missing policy type. ","") & IF($Q662="","Missing garaging state. ","") & IF($R662="","Missing garaging ZIP. ","") & IF($S662="","Missing cat zone. ","") & IF($V662="","Missing valuation basis. ","") & IF($W662="","Missing PD deductible. ","") & IF($X662="","Missing liability limit. ","") & IF($AB662="","Missing technical premium. ","") & IF($AF662="","Missing surplus lines tax %. ",""))="","PASS","FAIL: "&TRIM(IF($A662="","Missing certificate ref. ","") & IF($C662="","Missing effective date. ","") & IF($D662="","Missing binding status. ","") & IF($E662="","Missing movement type. ","") & IF($I662="","Missing make. ","") & IF($L662="","Missing vehicle class. ","") & IF($M662="","Missing agreed value. ","") & IF($N662="","Missing policy type. ","") & IF($Q662="","Missing garaging state. ","") & IF($R662="","Missing garaging ZIP. ","") & IF($S662="","Missing cat zone. ","") & IF($V662="","Missing valuation basis. ","") & IF($W662="","Missing PD deductible. ","") & IF($X662="","Missing liability limit. ","") & IF($AB662="","Missing technical premium. ","") & IF($AF662="","Missing surplus lines tax %. ","")))) | AY662: =IF($M662="","",IF(ISNUMBER($M662),IF($M662>=Header!$C$18,"YES — refer","No"),"")) | AZ662: =IF($AD662="","",IF(ISNUMBER($AD662),IF($AD662<Header!$C$20,"BELOW MIN PREMIUM","OK"),"")) | BA662: Yes | BB662: Yes | BC662: Synthetic demo data | BE662: =IF(OR($A662="",$L662="",$H662=""),"",IF(AND(LEFT($L662,2)="06",$H662>1945),"FAIL - pre-war class, year "&$H662,IF(AND(LEFT($L662,2)="07",OR($H662<1946,$H662>1972)),"FAIL - 1946-72 class, year "&$H662,IF(AND(LEFT($L662,2)="08",OR($H662<1973,$H662>1999)),"FAIL - 1973-99 class, year "&$H662,IF(AND(LEFT($L662,2)="09",OR($H662<2000,$H662>2010)),"FAIL - 2000-10 class, year "&$H662,"OK"))))) | BF662: =IF($AD662="","",IF(ROUND($AO662+$AP662+$AQ662-$AD662,2)=0,"OK","FAIL - out by "&TEXT($AO662+$AP662+$AQ662-$AD662,"$0.00")))

Sheet Reconciliation
A1: UNDERWRITING BORDEREAUX — RECONCILIATION AND CONTROL CHECKS
A2: Run every check before submitting. A bordereaux with missing mandatory fields or a panel that does not sign 100% will be rejected.
B4: SECTION A — PREMIUM RECONCILIATION
B5: TOTAL GROSS WRITTEN PREMIUM (bound risks, 100%) | C5: =SUMIF('UW Bordereaux'!$D$5:$D$662,"Bound*",'UW Bordereaux'!$AD$5:$AD$662)
B6: less: total commission (100%) | C6: =-SUMIF('UW Bordereaux'!$D$5:$D$662,"Bound*",'UW Bordereaux'!$AN$5:$AN$662)
B7: NET PREMIUM TO CAPACITY (100%) | C7: =SUMIF('UW Bordereaux'!$D$5:$D$662,"Bound*",'UW Bordereaux'!$AQ$5:$AQ$662)
B8: check: GWP less commission | C8: =C5+C6-C7
B9: VARIANCE (should be zero) | C9: =C8 | D9: =IF(ABS(C9)<1,"AGREES","INVESTIGATE — variance exceeds $1")
B10: Total policy fees collected | C10: =SUMIF('UW Bordereaux'!$D$5:$D$662,"Bound*",'UW Bordereaux'!$AE$5:$AE$662)
B11: Total surplus lines tax collected | C11: =SUMIF('UW Bordereaux'!$D$5:$D$662,"Bound*",'UW Bordereaux'!$AH$5:$AH$662)
B12: TOTAL DUE FROM INSUREDS | C12: =SUMIF('UW Bordereaux'!$D$5:$D$662,"Bound*",'UW Bordereaux'!$AI$5:$AI$662)
B13: Sum of GWP + fees + tax (check) | C13: =C5+C10+C11
B14: VARIANCE (should be zero) | C14: =C12-C13 | D14: =IF(ABS(C14)<1,"AGREES","INVESTIGATE — variance exceeds $1")
B15: Lead syndicate GWP at signed line | C15: =SUMIF('UW Bordereaux'!$D$5:$D$662,"Bound*",'UW Bordereaux'!$AD$5:$AD$662)*Header!$D$24
B16: Panel total GWP at signed line | C16: =SUMIF('UW Bordereaux'!$D$5:$D$662,"Bound*",'UW Bordereaux'!$AD$5:$AD$662)*Header!$D$34
B18: SECTION B — SUBMISSION CONTROL CHECKS
B19: Check | C19: Result | D19: Notes
B20: Every bound risk has a certificate number | C20: =IF(COUNTIFS('UW Bordereaux'!$D$5:$D$662,"Bound*",'UW Bordereaux'!$A$5:$A$662,"")=0,"PASS","FAIL — "&COUNTIFS('UW Bordereaux'!$D$5:$D$662,"Bound*",'UW Bordereaux'!$A$5:$A$662,"")&" bound risks missing certificate")
B21: Every row has a binding status | C21: =IF(SUMPRODUCT((LEN('UW Bordereaux'!$A$5:$A$662)>0)*(LEN('UW Bordereaux'!$D$5:$D$662)=0))=0,"PASS","FAIL — "&SUMPRODUCT((LEN('UW Bordereaux'!$A$5:$A$662)>0)*(LEN('UW Bordereaux'!$D$5:$D$662)=0))&" rows missing status")
B22: Effective date present on all bound risks | C22: =IF(COUNTIFS('UW Bordereaux'!$D$5:$D$662,"Bound*",'UW Bordereaux'!$C$5:$C$662,"")=0,"PASS","FAIL — "&COUNTIFS('UW Bordereaux'!$D$5:$D$662,"Bound*",'UW Bordereaux'!$C$5:$C$662,"")&" bound risks missing effective date")
B23: Technical premium entered on all bound risks | C23: =IF(COUNTIFS('UW Bordereaux'!$D$5:$D$662,"Bound*",'UW Bordereaux'!$AB$5:$AB$662,"")=0,"PASS","FAIL — "&COUNTIFS('UW Bordereaux'!$D$5:$D$662,"Bound*",'UW Bordereaux'!$AB$5:$AB$662,"")&" bound risks missing technical premium")
B24: Surplus lines tax % entered on all bound risks | C24: =IF(COUNTIFS('UW Bordereaux'!$D$5:$D$662,"Bound*",'UW Bordereaux'!$AF$5:$AF$662,"")=0,"PASS","FAIL — "&COUNTIFS('UW Bordereaux'!$D$5:$D$662,"Bound*",'UW Bordereaux'!$AF$5:$AF$662,"")&" bound risks missing SL tax rate") | F24: Verify rate with the stamping office before invoicing. Do not rely on defaults.
B25: No negative agreed values | C25: =IF(SUMPRODUCT(('UW Bordereaux'!$M$5:$M$662<0)*('UW Bordereaux'!$A$5:$A$662<>""))=0,"PASS","FAIL — negative agreed value detected")
B26: No agreed value below programme minimum ($100,000) | C26: =IF(SUMPRODUCT(('UW Bordereaux'!$M$5:$M$662<100000)*('UW Bordereaux'!$M$5:$M$662>0)*('UW Bordereaux'!$A$5:$A$662<>""))=0,"PASS","FAIL — "&SUMPRODUCT(('UW Bordereaux'!$M$5:$M$662<100000)*('UW Bordereaux'!$M$5:$M$662>0)*('UW Bordereaux'!$A$5:$A$662<>""))&" risks below $100,000 minimum")
B27: Syndicate panel signs 100% | C27: =IF(ROUND(Header!$D$34,4)=1,"PASS","FAIL — panel signs "&TEXT(Header!$D$34,"0.00%")&", must equal 100%")
B28: Rate adequacy — no risk below 85% | C28: =IF(COUNTIFS('UW Bordereaux'!$AJ$5:$AJ$662,"<0.85",'UW Bordereaux'!$D$5:$D$662,"Bound*")=0,"PASS","WARN — "&COUNTIFS('UW Bordereaux'!$AJ$5:$AJ$662,"<0.85",'UW Bordereaux'!$D$5:$D$662,"Bound*")&" risks below 85% rate adequacy") | F28: Warning only — not a hard stop. Refer risks below 85% to the lead syndicate.
B29: Risks at or above auto-bind limit | C29: =COUNTIFS('UW Bordereaux'!$M$5:$M$662,">="&Header!$C$18,'UW Bordereaux'!$D$5:$D$662,"Bound*")&" risk(s) at or above $2m AV — confirm individual referral is on file"
B30: Risks bound beyond discount authority | C30: =COUNTIF('UW Bordereaux'!$AK$5:$AK$662,"BEYOND AUTHORITY")&" risk(s) — confirm approval is on file in the Referral Log"
B31: Mandatory field check — all rows passing | C31: =IF(COUNTIF('UW Bordereaux'!$AW$5:$AW$662,"FAIL*")=0,"PASS — all mandatory fields complete","FAIL — "&COUNTIF('UW Bordereaux'!$AW$5:$AW$662,"FAIL*")&" rows with missing mandatory fields") | F31: Do not submit until all rows show PASS in column AW of the bordereaux.
B33: Vehicle class matches vehicle year | C33: =IF(COUNTIF('UW Bordereaux'!$BE$5:$BE$662,"FAIL*")=0,"PASS","FAIL - "&COUNTIF('UW Bordereaux'!$BE$5:$BE$662,"FAIL*")&" rows where vehicle year falls outside its class era")
B34: Every row foots: broker + Torque + net = GWP | C34: =IF(COUNTIF('UW Bordereaux'!$BF$5:$BF$662,"FAIL*")=0,"PASS - all rows foot to the cent","FAIL - "&COUNTIF('UW Bordereaux'!$BF$5:$BF$662,"FAIL*")&" rows do not foot")
B35: Commission splits sum to total ceding rate | C35: =IF(ROUND(Header!$K$3+Header!$M$3-Header!$I$3,6)=0,"PASS","FAIL - broker + Torque <> total ceding")
B36: 10 markets each at a 10% line, panel = 100% | C36: =IF(AND(ROUND(Header!$D$34,6)=1,COUNTIF(Header!$D$24:$D$33,0.1)=10),"PASS - 10 markets at 10% each","CHECK - lines are not 10 x 10%")
B39: COMMISSION RECONCILIATION
B40: Gross written premium (100%) | C40: =SUMIF('UW Bordereaux'!$D$5:$D$662,"Bound*",'UW Bordereaux'!$AD$5:$AD$662)
B41: Broker commission 12.5% | C41: =SUMIF('UW Bordereaux'!$D$5:$D$662,"Bound*",'UW Bordereaux'!$AO$5:$AO$662)
B42: Torque (MGA) commission 12.5% | C42: =SUMIF('UW Bordereaux'!$D$5:$D$662,"Bound*",'UW Bordereaux'!$AP$5:$AP$662)
B43: Net to capacity 75% | C43: =SUMIF('UW Bordereaux'!$D$5:$D$662,"Bound*",'UW Bordereaux'!$AQ$5:$AQ$662)
B44: Sum of the three components | C44: =C41+C42+C43
B45: VARIANCE TO GWP | C45: =C44-C40 | D45: =IF(ABS(C45)<0.005,"AGREES to the cent","INVESTIGATE - components do not foot")
B46: Broker as % of GWP | C46: =IFERROR(C41/C40,0)
B47: Torque as % of GWP | C47: =IFERROR(C42/C40,0)
B48: Net to capacity as % of GWP | C48: =IFERROR(C43/C40,0)
B49: Each 10% line receives (% of GWP) | C49: =IFERROR(C43/C40*0.1,0)
B51: Rounding: broker and Torque commission are each ROUNDed to 2 decimals; net to capacity is derived as GWP less the two rounded commissions. Every row therefore foots to the cent and the book total foots exactly - no rounding plug is ever required.

Sheet Field Definitions
A1: UNDERWRITING BORDEREAUX — FIELD DEFINITIONS
A2: Every column explained, with population rules and source.
B4: Col | C4: Field | D4: Type | E4: Source / notes
B5: A | C5: Certificate / policy ref | D5: Free text | E5: Your unique certificate number for this risk. Must be consistent across all submissions and across both the claims and underwriting bordereaux for the same policy.
B6: B | C6: Named insured | D6: Free text
B7: C | C7: Effective date | D7: Date
B8: D | C8: Binding status | D8: Drop-down
B9: E | C9: Movement type | D9: Drop-down
B10: F | C10: UMR | D10: Free text
B11: G | C11: Year of account | D11: CALCULATED | E11: Calculated from the effective date. Lloyd's accounts are managed by year of account; do not use the reporting period date.
B12: H | C12: Vehicle year | D12: Number
B13: I | C13: Make | D13: Free text
B14: J | C14: Model | D14: Free text
B15: K | C15: VIN / chassis | D15: Free text
B16: L | C16: Vehicle class | D16: Drop-down
B17: M | C17: Agreed value (USD) | D17: Currency
B18: N | C18: Policy type | D18: Drop-down
B19: O | C19: Usage description | D19: Free text
B20: P | C20: Annual mileage band | D20: Free text
B21: Q | C21: Garaging state | D21: Free text
B22: R | C22: Garaging ZIP | D22: Free text
B23: S | C23: Catastrophe zone | D23: Drop-down
B24: T | C24: Zone multiplier | D24: CALCULATED | E24: Calculated from the catastrophe zone using the multipliers on the Natural Catastrophe sheet. Feeds into the cat load component of the technical premium.
B25: U | C25: Cat deductible | D25: Free text
B26: V | C26: Valuation basis | D26: Drop-down
B27: W | C27: PD deductible | D27: Free text
B28: X | C28: Liability limit (CSL) | D28: Drop-down
B29: Y | C29: Endorsements / special terms | D29: Free text
B30: Z | C30: Conditions | D30: Free text
B31: AA | C31: Surplus lines / admitted | D31: Drop-down
B32: AB | C32: Technical premium (100%) | D32: Currency | E32: Enter the technical premium from the Portfolio Register or the Rating Engine for this risk. It must reflect the rate-adequate price before any UW judgement adjustment.
B33: AC | C33: UW judgement adj % | D33: Percentage | E33: The adjustment applied above or below technical. Negative = below. Feeds the GWP calculation. Must be consistent with the value entered on the Portfolio Register.
B34: AD | C34: GROSS WRITTEN PREMIUM (100%) | D34: CALCULATED | E34: Calculated: technical premium × (1 + UW judgement adjustment %). Report at 100% of the risk regardless of syndicate share.
B35: AE | C35: Policy fee (100%) | D35: Currency
B36: AF | C36: Inspection / appraisal fee | D36: Currency
B37: AG | C37: Surplus lines tax % | D37: Percentage
B38: AH | C38: Surplus lines tax $ | D38: CALCULATED | E38: Calculated: (GWP + policy fee + inspection fee) × surplus lines tax %. Verify the rate for every state — rates change frequently and the formula carries the rate you enter, not a live lookup.
B39: AI | C39: Stamping fee $ | D39: Currency
B40: AJ | C40: TOTAL DUE FROM INSURED (100%) | D40: CALCULATED | E40: Calculated: GWP + policy fee + inspection fee + surplus lines tax + stamping fee. This is the gross invoice amount before any commission is netted off.
B41: AK | C41: Rate adequacy check | D41: CALCULATED | E41: Calculated: total due ÷ technical premium. The portfolio rate adequacy in the Header summary uses GWP; this cell uses total due including fees, so it will be slightly above 100% even at technical.
B42: AL | C42: Bind band | D42: Drop-down | E42: Whether the risk was written above, at, or below technical rate. BEYOND AUTHORITY means the discount exceeded the authority limit. Must match the Portfolio Register for the same risk.
B43: AM | C43: Total ceding commission % | D43: CALCULATED | E43: Linked from the Commission Structure sheet. If the commission rate is specific to this risk (e.g. a non-standard agreement), override manually and note it in the Notes column.
B44: AN | C44: Commission $ (100%) | D44: CALCULATED | E44: From Portfolio Register
B45: AO | C45: Broker commission $ (100%) | D45: CALCULATED | E45: From Portfolio Register
B46: AP | C46: MGA net commission $ (100%) | D46: CALCULATED | E46: From Portfolio Register
B47: AQ | C47: NET PREMIUM TO CAPACITY (100%) | D47: CALCULATED | E47: GWP less total ceding commission. This is what reaches the Lloyd's trust fund before deduction of Lloyd's charges, central fund contributions and reinsurance.
B48: AR | C48: GWP at signed line | D48: CALCULATED | E48: The lead syndicate's proportional share of GWP. Uses the lead line from the Header panel table; adjust if the lead line differs by risk.
B49: AS | C49: Tech prem at signed line | D49: CALCULATED
B50: AT | C50: Technical rate per $100 | D50: CALCULATED
B51: AU | C51: Charged rate per $100 | D51: CALCULATED
B52: AV | C52: Portfolio rate adequacy | D52: CALCULATED
B53: AW | C53: Profit commission accrual | D53: CALCULATED
B54: AX | C54: MANDATORY FIELD CHECK | D54: CALCULATED | E54: Calculated. Reads PASS when all sixteen mandatory fields are populated, FAIL followed by a description of what is missing when any are blank. Do not submit rows showing FAIL.
B55: AY | C55: Above auto-bind limit? | D55: CALCULATED | E55: Calculated against the threshold in Header row 18. A YES means an individual referral must be on file in the Referral Log before this row is submitted.
B56: AZ | C56: Min premium met? | D56: CALCULATED | E56: Calculated against the minimum premium in Header row 20. BELOW MIN PREMIUM means the premium must be loaded to the minimum, subject to the insured's consent.
B57: BA | C57: Surplus lines tax verified? | D57: Drop-down
B58: BB | C58: Signed by approver? | D58: Drop-down
B59: BC | C59: Notes | D59: Free text

Sheet Lists
A1: VALIDATION LISTS
A2: Source of every drop-down in this workbook.
A4: Movement Type | B4: Binding Status | C4: Policy Type | D4: Vehicle Class | E4: Valuation Basis | F4: Liability Limit | G4: Cat Zone | H4: Bind Band | I4: Currency | J4: Yes No | K4: Surplus Lines Admitted
A5: New business | B5: Bound - within authority | C5: Personal | D5: 01 - Luxury Sedan / SUV | E5: Agreed Value | F5: $300,000 CSL | G5: Tier 1 - Coastal wind / surge (0-1 mile, FEMA V or Coastal A) | H5: Above technical | I5: USD | J5: Yes | K5: Surplus Lines
A6: Renewal | B6: Bound - approved referral | C6: Commercial | D6: 02 - Sports / GT | E6: Agreed Value + Appreciation clause | F6: $500,000 CSL | G6: Tier 2 - Coastal wind (1-25 miles) | H6: At technical | I6: GBP | J6: No | K6: Admitted
A7: Mid-term endorsement | B7: Quoted - not yet bound | D7: 03 - Supercar | E7: Stated Value (up to) | F7: $1,000,000 CSL | G7: Tier 3 - Coastal wind (25-100 miles) | H7: BELOW technical | I7: EUR | K7: London Direct
A8: Mid-term cancellation | B8: Declined | D8: 04 - Hypercar | E8: Actual Cash Value | F8: $2,000,000 CSL | G8: Inland - hurricane remnant only (100+ miles) | H8: BEYOND AUTHORITY | I8: CAD
A9: Reinstatement | B9: Cancelled | D9: 05 - Limited Edition / Track-Focused | F9: $5,000,000 CSL | G9: Severe convective - hail alley (high)
A10: Correction / restatement | B10: Lapsed | D10: 06 - Vintage Pre-War (pre-1946) | F10: $10,000,000 CSL | G10: Severe convective - hail / tornado (moderate)
A11: No change this period | B11: Void | D11: 07 - Post-War Classic (1946-1972) | G11: Wildfire - WUI high hazard
D12: 08 - Modern Classic (1973-1999) | G12: Wildfire - moderate hazard
D13: 09 - Youngtimer / Collectible (2000-2010) | G13: Earthquake - high (CA, Cascadia, New Madrid)
D14: 10 - Competition / Race Car | G14: Flood - FEMA SFHA (zone A / AE / V)
D15: 11 - Restomod / Coachbuilt / Bespoke | G15: Winter freeze / ice / severe road salt
D16: 12 - Performance EV / Electric Hyper | G16: Low hazard - inland benign
